[{"ISSUE_DATE":"Sep 8, 2023 13:56:46","RECEIPT_NO":"85046\/26125","METER_NO":"'07147897461","ACCT_NAME":"AKEMI DELBIRT","ACCT_NO":"P06627100","VOUCHER_NO":"0305 9233 6239 5936 2625","TOTAL_KWH":"114.6","TOTAL_VALUE":"$39.60"},{"ISSUE_DATE":"Sep 8, 2023 13:57:27","RECEIPT_NO":"85046\/26126","METER_NO":"'07137643925","ACCT_NAME":"AKEMI KALEB","ACCT_NO":"P06559500","VOUCHER_NO":"4232 1601 4954 4667 0574","TOTAL_KWH":"114.6","TOTAL_VALUE":"$39.60"},{"ISSUE_DATE":"Sep 8, 2023 13:57:41","RECEIPT_NO":"85046\/26127","METER_NO":"'07053085432","ACCT_NAME":"ALVINA M. RIUNGEL","ACCT_NO":"P06210500","VOUCHER_NO":"0623 6730 7793 6098 4423","TOTAL_KWH":"132.1","TOTAL_VALUE":"$39.60"},{"ISSUE_DATE":"Sep 8, 2023 13:57:54","RECEIPT_NO":"85046\/26128","METER_NO":"'07144537078","ACCT_NAME":"ANGELINE & INOSENCIO METEOLECHOL","ACCT_NO":"P06593400","VOUCHER_NO":"3931 4113 6288 8624 5785","TOTAL_KWH":"114.6","TOTAL_VALUE":"$39.60"},{"ISSUE_DATE":"Sep 8, 2023 13:58:20","RECEIPT_NO":"85046\/26129","METER_NO":"'07097967876","ACCT_NAME":"BAILEY THEODORE","ACCT_NO":"P06448900","VOUCHER_NO":"3764 5373 6322 5848 3354","TOTAL_KWH":"150.0","TOTAL_VALUE":"$39.60"},{"ISSUE_DATE":"Sep 8, 2023 13:59:08","RECEIPT_NO":"85046\/26130","METER_NO":"'37263735872","ACCT_NAME":"BARMELIO IBUTIRANG","ACCT_NO":"P06565200","VOUCHER_NO":"5375 9701 5370 8229 1883","TOTAL_KWH":"150.0","TOTAL_VALUE":"$39.60"},{"ISSUE_DATE":"Sep 8, 2023 13:59:20","RECEIPT_NO":"85046\/26131","METER_NO":"'07097962364","ACCT_NAME":"BIKEI SBAL","ACCT_NO":"P06410500","VOUCHER_NO":"4084 4984 4552 7258 3958","TOTAL_KWH":"114.6","TOTAL_VALUE":"$39.60"},{"ISSUE_DATE":"Sep 8, 2023 13:59:30","RECEIPT_NO":"85046\/26132","METER_NO":"'07050042287","ACCT_NAME":"BLANK OLSINGCH","ACCT_NO":"P06318600","VOUCHER_NO":"7114 8503 4407 9429 5352","TOTAL_KWH":"114.6","TOTAL_VALUE":"$39.60"},{"ISSUE_DATE":"Sep 8, 2023 13:59:40","RECEIPT_NO":"85046\/26133","METER_NO":"'07077095656","ACCT_NAME":"BRADLEY AUGUSTINE","ACCT_NO":"P06366000","VOUCHER_NO":"6100 8636 6348 8468 9323","TOTAL_KWH":"150.0","TOTAL_VALUE":"$39.60"},{"ISSUE_DATE":"Sep 8, 2023 13:59:55","RECEIPT_NO":"85046\/26134","METER_NO":"'07144540668","ACCT_NAME":"BUCK MILLER","ACCT_NO":"P06614900","VOUCHER_NO":"4812 2160 3755 3521 5795","TOTAL_KWH":"150.0","TOTAL_VALUE":"$39.60"},{"ISSUE_DATE":"Sep 8, 2023 14:00:06","RECEIPT_NO":"85046\/26135","METER_NO":"'07053085614","ACCT_NAME":"CAMILUS NGIRMERIIL","ACCT_NO":"P06193400","VOUCHER_NO":"2359 9072 2518 2968 8135","TOTAL_KWH":"114.6","TOTAL_VALUE":"$39.60"},{"ISSUE_DATE":"Sep 8, 2023 14:00:16","RECEIPT_NO":"85046\/26136","METER_NO":"'07055922640","ACCT_NAME":"CECILIA IKYASANG","ACCT_NO":"P06329200","VOUCHER_NO":"5197 3872 4211 8595 9769","TOTAL_KWH":"104.1","TOTAL_VALUE":"$39.60"},{"ISSUE_DATE":"Sep 8, 2023 14:00:26","RECEIPT_NO":"85046\/26137","METER_NO":"'07053087230","ACCT_NAME":"CLEOFAS IYAR","ACCT_NO":"P06624500","VOUCHER_NO":"2234 8231 6104 9578 1640","TOTAL_KWH":"138.6","TOTAL_VALUE":"$39.60"},{"ISSUE_DATE":"Sep 8, 2023 14:00:35","RECEIPT_NO":"85046\/26138","METER_NO":"'07144537870","ACCT_NAME":"DEBORAH NIRO","ACCT_NO":"P06599100","VOUCHER_NO":"1579 6014 4116 7861 0204","TOTAL_KWH":"114.6","TOTAL_VALUE":"$39.60"},{"ISSUE_DATE":"Sep 8, 2023 14:00:49","RECEIPT_NO":"85046\/26139","METER_NO":"'07144536971","ACCT_NAME":"EDBURG MABEL","ACCT_NO":"P06593500","VOUCHER_NO":"4177 8041 6802 4539 8487","TOTAL_KWH":"132.1","TOTAL_VALUE":"$39.60"},{"ISSUE_DATE":"Sep 8, 2023 14:01:02","RECEIPT_NO":"85046\/26140","METER_NO":"'07144545758","ACCT_NAME":"DELBECHEL ICHIRO","ACCT_NO":"P06369600","VOUCHER_NO":"3420 6701 1681 4930 9093","TOTAL_KWH":"150.0","TOTAL_VALUE":"$39.60"},{"ISSUE_DATE":"Sep 8, 2023 14:01:13","RECEIPT_NO":"85046\/26141","METER_NO":"'07144536997","ACCT_NAME":"DELMA SIKONG","ACCT_NO":"P06593700","VOUCHER_NO":"0522 1287 4170 9021 6920","TOTAL_KWH":"132.1","TOTAL_VALUE":"$39.60"},{"ISSUE_DATE":"Sep 8, 2023 14:01:25","RECEIPT_NO":"85046\/26142","METER_NO":"'07097968494","ACCT_NAME":"DENIKA SAKUMA","ACCT_NO":"P06464500","VOUCHER_NO":"6707 6464 3054 0007 9244","TOTAL_KWH":"114.6","TOTAL_VALUE":"$39.60"},{"ISSUE_DATE":"Sep 8, 2023 14:01:35","RECEIPT_NO":"85046\/26143","METER_NO":"'07147931468","ACCT_NAME":"DERYCK DEMK","ACCT_NO":"P06666400","VOUCHER_NO":"5968 8925 7543 3626 1606","TOTAL_KWH":"150.0","TOTAL_VALUE":"$39.60"},{"ISSUE_DATE":"Sep 8, 2023 14:01:44","RECEIPT_NO":"85046\/26144","METER_NO":"'07137644337","ACCT_NAME":"DESTINY TROLII","ACCT_NO":"P06556000","VOUCHER_NO":"0112 8403 9452 6045 9478","TOTAL_KWH":"114.6","TOTAL_VALUE":"$39.60"},{"ISSUE_DATE":"Sep 8, 2023 14:01:56","RECEIPT_NO":"85046\/26145","METER_NO":"'07110879074","ACCT_NAME":"DEXTER DECHERONG","ACCT_NO":"P06581600","VOUCHER_NO":"5649 7382 4099 1232 2947","TOTAL_KWH":"150.0","TOTAL_VALUE":"$39.60"},{"ISSUE_DATE":"Sep 8, 2023 14:02:05","RECEIPT_NO":"85046\/26146","METER_NO":"'07110879330","ACCT_NAME":"DIANA HESUS","ACCT_NO":"P06584300","VOUCHER_NO":"4132 5796 4164 2454 9989","TOTAL_KWH":"150.0","TOTAL_VALUE":"$39.60"},{"ISSUE_DATE":"Sep 8, 2023 14:02:15","RECEIPT_NO":"85046\/26147","METER_NO":"'07077091655","ACCT_NAME":"DIRREOU MELIMARANG","ACCT_NO":"P06342300","VOUCHER_NO":"6519 9621 5887 8611 6661","TOTAL_KWH":"132.1","TOTAL_VALUE":"$39.60"},{"ISSUE_DATE":"Sep 8, 2023 14:02:28","RECEIPT_NO":"85046\/26148","METER_NO":"'07106548923","ACCT_NAME":"DOMININA KUNIHIRO","ACCT_NO":"P06205800","VOUCHER_NO":"3770 3228 5865 9293 5361","TOTAL_KWH":"114.6","TOTAL_VALUE":"$39.60"},{"ISSUE_DATE":"Sep 8, 2023 14:02:41","RECEIPT_NO":"85046\/26149","METER_NO":"'07110215386","ACCT_NAME":"EDEN BENHART","ACCT_NO":"P06546000","VOUCHER_NO":"1729 4712 5884 2564 9789","TOTAL_KWH":"135.4","TOTAL_VALUE":"$39.60"},{"ISSUE_DATE":"Sep 8, 2023 14:02:51","RECEIPT_NO":"85046\/26150","METER_NO":"'07077091440","ACCT_NAME":"EDWIN MAMORU","ACCT_NO":"P06343100","VOUCHER_NO":"1142 3428 7212 3429 8676","TOTAL_KWH":"114.6","TOTAL_VALUE":"$39.60"},{"ISSUE_DATE":"Sep 8, 2023 14:03:00","RECEIPT_NO":"85046\/26151","METER_NO":"'07107715695","ACCT_NAME":"MARTIN UCHERBELAU","ACCT_NO":"P06235200","VOUCHER_NO":"3009 9533 4104 9420 6539","TOTAL_KWH":"117.1","TOTAL_VALUE":"$39.60"},{"ISSUE_DATE":"Sep 8, 2023 14:03:11","RECEIPT_NO":"85046\/26152","METER_NO":"'07097965375","ACCT_NAME":"ELLENA TADASHI","ACCT_NO":"P06435200","VOUCHER_NO":"4293 1067 4322 9731 6073","TOTAL_KWH":"132.1","TOTAL_VALUE":"$39.60"},{"ISSUE_DATE":"Sep 8, 2023 14:03:22","RECEIPT_NO":"85046\/26153","METER_NO":"'07097969666","ACCT_NAME":"ELOISE YSAOL","ACCT_NO":"P06504200","VOUCHER_NO":"0341 1869 0769 6308 0371","TOTAL_KWH":"114.6","TOTAL_VALUE":"$39.60"},{"ISSUE_DATE":"Sep 8, 2023 14:03:50","RECEIPT_NO":"85046\/26154","METER_NO":"'07110215204","ACCT_NAME":"ELSIE AARON","ACCT_NO":"P06523700","VOUCHER_NO":"6267 9630 3054 3195 5679","TOTAL_KWH":"133.6","TOTAL_VALUE":"$39.60"},{"ISSUE_DATE":"Sep 8, 2023 14:04:08","RECEIPT_NO":"85046\/26155","METER_NO":"'07110215337","ACCT_NAME":"DAVIS MESUBED","ACCT_NO":"P06284600","VOUCHER_NO":"1988 6161 2370 4778 7050","TOTAL_KWH":"132.1","TOTAL_VALUE":"$39.60"},{"ISSUE_DATE":"Sep 8, 2023 14:04:19","RECEIPT_NO":"85046\/26156","METER_NO":"'07097969971","ACCT_NAME":"EVELYN ANDREAS","ACCT_NO":"P06290100","VOUCHER_NO":"3997 9342 1622 7589 0332","TOTAL_KWH":"150.0","TOTAL_VALUE":"$39.60"},{"ISSUE_DATE":"Sep 8, 2023 14:04:31","RECEIPT_NO":"85046\/26157","METER_NO":"'07057818895","ACCT_NAME":"EVELYN SEKLII","ACCT_NO":"P06202700","VOUCHER_NO":"2949 3021 1896 7722 3835","TOTAL_KWH":"132.1","TOTAL_VALUE":"$39.60"},{"ISSUE_DATE":"Sep 8, 2023 14:05:12","RECEIPT_NO":"85046\/26158","METER_NO":"'07050105894","ACCT_NAME":"KIMIYO NAKAMURA RM#5","ACCT_NO":"P06360800","VOUCHER_NO":"5838 2118 2558 6740 6182","TOTAL_KWH":"135.4","TOTAL_VALUE":"$39.60"},{"ISSUE_DATE":"Sep 8, 2023 14:07:41","RECEIPT_NO":"85046\/26159","METER_NO":"'07053086901","ACCT_NAME":"FELIX OSILEK","ACCT_NO":"P06587700","VOUCHER_NO":"1445 9664 2566 9039 4733","TOTAL_KWH":"114.6","TOTAL_VALUE":"$39.60"},{"ISSUE_DATE":"Sep 8, 2023 14:07:54","RECEIPT_NO":"85046\/26160","METER_NO":"'07057781473","ACCT_NAME":"FRANCIS NGOTEL","ACCT_NO":"P06205300","VOUCHER_NO":"2645 1357 4748 1806 9770","TOTAL_KWH":"132.1","TOTAL_VALUE":"$39.60"},{"ISSUE_DATE":"Sep 8, 2023 14:08:05","RECEIPT_NO":"85046\/26161","METER_NO":"'07110218638","ACCT_NAME":"FRANZ TELLEI","ACCT_NO":"P06531600","VOUCHER_NO":"7042 3043 1133 3591 5039","TOTAL_KWH":"150.0","TOTAL_VALUE":"$39.60"},{"ISSUE_DATE":"Sep 8, 2023 14:08:17","RECEIPT_NO":"85046\/26162","METER_NO":"'07110218877","ACCT_NAME":"GAILEEN GAILLIARD","ACCT_NO":"P06526700","VOUCHER_NO":"3403 9149 9757 1748 7914","TOTAL_KWH":"120.5","TOTAL_VALUE":"$39.60"},{"ISSUE_DATE":"Sep 8, 2023 14:08:28","RECEIPT_NO":"85046\/26163","METER_NO":"'07101017536","ACCT_NAME":"GORDON TKEL","ACCT_NO":"P06396100","VOUCHER_NO":"0414 9726 4560 7658 8997","TOTAL_KWH":"150.0","TOTAL_VALUE":"$39.60"},{"ISSUE_DATE":"Sep 8, 2023 14:08:41","RECEIPT_NO":"85046\/26164","METER_NO":"'07055922731","ACCT_NAME":"GRANT INGAIS","ACCT_NO":"P06329300","VOUCHER_NO":"1089 3499 3879 7857 2653","TOTAL_KWH":"132.1","TOTAL_VALUE":"$39.60"},{"ISSUE_DATE":"Sep 8, 2023 14:08:54","RECEIPT_NO":"85046\/26165","METER_NO":"'07107715992","ACCT_NAME":"HAINRICK HUZIKO","ACCT_NO":"P06496200","VOUCHER_NO":"0591 1227 5425 4418 0882","TOTAL_KWH":"150.0","TOTAL_VALUE":"$39.60"},{"ISSUE_DATE":"Sep 8, 2023 14:09:08","RECEIPT_NO":"85046\/26166","METER_NO":"'07097966985","ACCT_NAME":"HAPPY OILOUCH","ACCT_NO":"P06451700","VOUCHER_NO":"7249 4012 0580 4045 6031","TOTAL_KWH":"150.0","TOTAL_VALUE":"$39.60"},{"ISSUE_DATE":"Sep 8, 2023 14:09:51","RECEIPT_NO":"85046\/26167","METER_NO":"'07077096035","ACCT_NAME":"HARUO SALVADOR","ACCT_NO":"P06367400","VOUCHER_NO":"6101 9092 7005 0619 0774","TOTAL_KWH":"150.0","TOTAL_VALUE":"$39.60"},{"ISSUE_DATE":"Sep 8, 2023 14:12:00","RECEIPT_NO":"85046\/26168","METER_NO":"'07147948892","ACCT_NAME":"HAYES MALSOL #2","ACCT_NO":"P06665500","VOUCHER_NO":"6408 0576 0643 3568 1360","TOTAL_KWH":"150.0","TOTAL_VALUE":"$39.60"},{"ISSUE_DATE":"Sep 8, 2023 14:12:11","RECEIPT_NO":"85046\/26169","METER_NO":"'07101016876","ACCT_NAME":"HESUS NGIRAILEMESANG","ACCT_NO":"P06274000","VOUCHER_NO":"7166 9102 6652 5721 4990","TOTAL_KWH":"132.1","TOTAL_VALUE":"$39.60"},{"ISSUE_DATE":"Sep 8, 2023 14:12:49","RECEIPT_NO":"85046\/26170","METER_NO":"'07147899103","ACCT_NAME":"HESUS TOWAI","ACCT_NO":"P06639200","VOUCHER_NO":"5658 3652 6617 3128 0678","TOTAL_KWH":"104.8","TOTAL_VALUE":"$27.67"},{"ISSUE_DATE":"Sep 8, 2023 14:13:08","RECEIPT_NO":"85046\/26171","METER_NO":"'07147931229","ACCT_NAME":"IDA NGIRMANG","ACCT_NO":"P06232200","VOUCHER_NO":"2583 6609 7573 1749 9732","TOTAL_KWH":"150.0","TOTAL_VALUE":"$39.60"},{"ISSUE_DATE":"Sep 8, 2023 14:13:19","RECEIPT_NO":"85046\/26172","METER_NO":"'07097962679","ACCT_NAME":"SIERRA ISALIAS","ACCT_NO":"P06413600","VOUCHER_NO":"7002 1786 5394 5385 9229","TOTAL_KWH":"150.0","TOTAL_VALUE":"$39.60"},{"ISSUE_DATE":"Sep 8, 2023 14:13:30","RECEIPT_NO":"85046\/26173","METER_NO":"'07077095516","ACCT_NAME":"SORCH V. MEYAR","ACCT_NO":"P06363400","VOUCHER_NO":"6037 1649 6508 0520 6916","TOTAL_KWH":"150.0","TOTAL_VALUE":"$39.60"},{"ISSUE_DATE":"Sep 8, 2023 14:13:42","RECEIPT_NO":"85046\/26174","METER_NO":"'07144544645","ACCT_NAME":"JASSMERE RENGULBAI & FELISA MAIDESIL","ACCT_NO":"P06615300","VOUCHER_NO":"6114 3645 0067 5303 1230","TOTAL_KWH":"114.6","TOTAL_VALUE":"$39.60"},{"ISSUE_DATE":"Sep 8, 2023 14:14:00","RECEIPT_NO":"85046\/26175","METER_NO":"'07110897993","ACCT_NAME":"JEFFREY RECHETUKER","ACCT_NO":"P06540400","VOUCHER_NO":"0520 6536 5923 9145 4908","TOTAL_KWH":"132.1","TOTAL_VALUE":"$39.60"},{"ISSUE_DATE":"Sep 8, 2023 14:14:18","RECEIPT_NO":"85046\/26176","METER_NO":"'37263736672","ACCT_NAME":"JENNIFER TORIBIONG","ACCT_NO":"P06578500","VOUCHER_NO":"6026 1512 2206 7637 4530","TOTAL_KWH":"150.0","TOTAL_VALUE":"$39.60"},{"ISSUE_DATE":"Sep 8, 2023 14:14:29","RECEIPT_NO":"85046\/26177","METER_NO":"'07057817798","ACCT_NAME":"JERMAEND ELIAS","ACCT_NO":"P06272400","VOUCHER_NO":"7313 2217 8630 3035 7218","TOTAL_KWH":"132.1","TOTAL_VALUE":"$39.60"},{"ISSUE_DATE":"Sep 8, 2023 14:14:40","RECEIPT_NO":"85046\/26178","METER_NO":"'07110879587","ACCT_NAME":"JEROME OITERONG","ACCT_NO":"P06317500","VOUCHER_NO":"7194 5225 5151 9172 9305","TOTAL_KWH":"114.6","TOTAL_VALUE":"$39.60"},{"ISSUE_DATE":"Sep 8, 2023 14:14:52","RECEIPT_NO":"85046\/26179","METER_NO":"'07082736732","ACCT_NAME":"JEROME RAMARUI","ACCT_NO":"P06385500","VOUCHER_NO":"1773 0968 5405 1305 0580","TOTAL_KWH":"120.7","TOTAL_VALUE":"$39.60"},{"ISSUE_DATE":"Sep 8, 2023 14:15:09","RECEIPT_NO":"85046\/26180","METER_NO":"'07110218661","ACCT_NAME":"JOHANA ADERKEROI","ACCT_NO":"P06531800","VOUCHER_NO":"6206 4165 1261 2029 5436","TOTAL_KWH":"150.0","TOTAL_VALUE":"$39.60"},{"ISSUE_DATE":"Sep 8, 2023 14:15:24","RECEIPT_NO":"85046\/26181","METER_NO":"'07147951284","ACCT_NAME":"DIAL PIZZA","ACCT_NO":"P06459800","VOUCHER_NO":"3255 3005 9610 4838 9613","TOTAL_KWH":"150.0","TOTAL_VALUE":"$39.60"},{"ISSUE_DATE":"Sep 8, 2023 14:15:39","RECEIPT_NO":"85046\/26182","METER_NO":"'07107715653","ACCT_NAME":"JOHN DECK TIMARONG","ACCT_NO":"P06494300","VOUCHER_NO":"0902 3226 0170 4775 2814","TOTAL_KWH":"114.6","TOTAL_VALUE":"$39.60"},{"ISSUE_DATE":"Sep 8, 2023 14:15:52","RECEIPT_NO":"85046\/26183","METER_NO":"'07097968478","ACCT_NAME":"JOLANDA WARREN","ACCT_NO":"P06463100","VOUCHER_NO":"2551 8940 0497 6097 3791","TOTAL_KWH":"117.5","TOTAL_VALUE":"$39.60"},{"ISSUE_DATE":"Sep 8, 2023 14:16:06","RECEIPT_NO":"85046\/26184","METER_NO":"'07147927656","ACCT_NAME":"JOSHUA OBAK","ACCT_NO":"P06674200","VOUCHER_NO":"4497 4955 4436 8723 8156","TOTAL_KWH":"138.6","TOTAL_VALUE":"$39.60"},{"ISSUE_DATE":"Sep 8, 2023 14:16:21","RECEIPT_NO":"85046\/26185","METER_NO":"'07147948967","ACCT_NAME":"RUDIMCH KURODA","ACCT_NO":"P06665800","VOUCHER_NO":"3319 1628 4020 9317 5451","TOTAL_KWH":"150.0","TOTAL_VALUE":"$39.60"},{"ISSUE_DATE":"Sep 8, 2023 14:16:36","RECEIPT_NO":"85046\/26186","METER_NO":"'07147900059","ACCT_NAME":"KAREN BREL","ACCT_NO":"P06632600","VOUCHER_NO":"2210 7153 1634 6105 3042","TOTAL_KWH":"150.0","TOTAL_VALUE":"$39.60"},{"ISSUE_DATE":"Sep 8, 2023 14:16:46","RECEIPT_NO":"85046\/26187","METER_NO":"'07144537482","ACCT_NAME":"KATO KATOSANG","ACCT_NO":"P06346300","VOUCHER_NO":"1480 8069 8679 9227 0167","TOTAL_KWH":"150.0","TOTAL_VALUE":"$39.60"},{"ISSUE_DATE":"Sep 8, 2023 14:16:57","RECEIPT_NO":"85046\/26188","METER_NO":"'07147916014","ACCT_NAME":"KATSUMI T. NGIRCHOKEBAI","ACCT_NO":"P06710800","VOUCHER_NO":"5061 3778 8312 2664 7645","TOTAL_KWH":"150.0","TOTAL_VALUE":"$39.60"},{"ISSUE_DATE":"Sep 8, 2023 14:17:10","RECEIPT_NO":"85046\/26189","METER_NO":"'07147948579","ACCT_NAME":"KAYLA OBEKETANG","ACCT_NO":"P06688100","VOUCHER_NO":"3334 4097 6859 4171 4202","TOTAL_KWH":"114.6","TOTAL_VALUE":"$39.60"},{"ISSUE_DATE":"Sep 8, 2023 14:17:23","RECEIPT_NO":"85046\/26190","METER_NO":"'07082736864","ACCT_NAME":"KIMIYO NAKAMURA RM#8","ACCT_NO":"P06385800","VOUCHER_NO":"0643 6826 8089 8129 2142","TOTAL_KWH":"114.6","TOTAL_VALUE":"$39.60"},{"ISSUE_DATE":"Sep 8, 2023 14:17:39","RECEIPT_NO":"85046\/26191","METER_NO":"'07110897233","ACCT_NAME":"KUKONG SAKAZIRO","ACCT_NO":"P06541300","VOUCHER_NO":"6136 5915 0136 2344 5129","TOTAL_KWH":"150.0","TOTAL_VALUE":"$39.60"},{"ISSUE_DATE":"Sep 8, 2023 14:17:53","RECEIPT_NO":"85046\/26192","METER_NO":"'07107718079","ACCT_NAME":"KUMER IDESMANG","ACCT_NO":"P06509200","VOUCHER_NO":"1520 2711 8604 7258 0157","TOTAL_KWH":"132.1","TOTAL_VALUE":"$39.60"},{"ISSUE_DATE":"Sep 8, 2023 14:18:05","RECEIPT_NO":"85046\/26193","METER_NO":"'07110892671","ACCT_NAME":"KYIOMI MITARO","ACCT_NO":"P06539000","VOUCHER_NO":"0352 1270 8640 7750 1172","TOTAL_KWH":"114.6","TOTAL_VALUE":"$39.60"},{"ISSUE_DATE":"Sep 8, 2023 14:18:17","RECEIPT_NO":"85046\/26194","METER_NO":"'07050042642","ACCT_NAME":"LADY NGIRATKAKL","ACCT_NO":"P06323200","VOUCHER_NO":"5704 1168 4237 8950 4036","TOTAL_KWH":"150.0","TOTAL_VALUE":"$39.60"},{"ISSUE_DATE":"Sep 8, 2023 14:18:29","RECEIPT_NO":"85046\/26195","METER_NO":"'07147930916","ACCT_NAME":"LAINE RUBEANG DOWNSTAIRS #2","ACCT_NO":"P06679000","VOUCHER_NO":"1719 8437 5742 4906 1206","TOTAL_KWH":"114.6","TOTAL_VALUE":"$39.60"},{"ISSUE_DATE":"Sep 8, 2023 14:19:38","RECEIPT_NO":"85046\/26196","METER_NO":"'07050042543","ACCT_NAME":"LALII OITERONG","ACCT_NO":"P06235400","VOUCHER_NO":"3917 1775 2682 0469 1985","TOTAL_KWH":"150.0","TOTAL_VALUE":"$39.60"},{"ISSUE_DATE":"Sep 8, 2023 14:19:49","RECEIPT_NO":"85046\/26197","METER_NO":"'07077091721","ACCT_NAME":"HOSEA INACIO","ACCT_NO":"P06340900","VOUCHER_NO":"0031 9113 6949 9166 3765","TOTAL_KWH":"132.1","TOTAL_VALUE":"$39.60"},{"ISSUE_DATE":"Sep 8, 2023 14:20:01","RECEIPT_NO":"85046\/26198","METER_NO":"'07110897324","ACCT_NAME":"LAWRENCE NGIRAROROU","ACCT_NO":"P06248500","VOUCHER_NO":"1603 6468 8424 6647 6136","TOTAL_KWH":"117.5","TOTAL_VALUE":"$39.60"},{"ISSUE_DATE":"Sep 8, 2023 14:20:12","RECEIPT_NO":"85046\/26199","METER_NO":"'07147910801","ACCT_NAME":"LAZARUS SMASERUI","ACCT_NO":"P06493400","VOUCHER_NO":"4427 4750 2685 5129 2810","TOTAL_KWH":"132.1","TOTAL_VALUE":"$39.60"},{"ISSUE_DATE":"Sep 8, 2023 14:20:24","RECEIPT_NO":"85046\/26200","METER_NO":"'07144543282","ACCT_NAME":"LEVITICUS LUKAS 2","ACCT_NO":"P06620700","VOUCHER_NO":"0183 4285 7170 9387 5435","TOTAL_KWH":"129.6","TOTAL_VALUE":"$39.60"},{"ISSUE_DATE":"Sep 8, 2023 14:20:34","RECEIPT_NO":"85046\/26201","METER_NO":"'07147949163","ACCT_NAME":"LILY IKEYA","ACCT_NO":"P06689900","VOUCHER_NO":"0523 1214 7711 8019 1166","TOTAL_KWH":"150.0","TOTAL_VALUE":"$39.60"},{"ISSUE_DATE":"Sep 8, 2023 14:20:46","RECEIPT_NO":"85046\/26202","METER_NO":"'07144537615","ACCT_NAME":"LOUISA NGIRAKED","ACCT_NO":"P06597700","VOUCHER_NO":"2639 3692 8719 5397 1803","TOTAL_KWH":"114.6","TOTAL_VALUE":"$39.60"},{"ISSUE_DATE":"Sep 8, 2023 14:20:55","RECEIPT_NO":"85046\/26203","METER_NO":"'07101016322","ACCT_NAME":"LOVELYN APRIL","ACCT_NO":"P06400400","VOUCHER_NO":"3842 5023 6823 5908 9751","TOTAL_KWH":"120.7","TOTAL_VALUE":"$39.60"},{"ISSUE_DATE":"Sep 8, 2023 14:21:07","RECEIPT_NO":"85046\/26204","METER_NO":"'07097967520","ACCT_NAME":"LUCY MARK","ACCT_NO":"P06234600","VOUCHER_NO":"2594 3522 8643 4834 5766","TOTAL_KWH":"114.6","TOTAL_VALUE":"$39.60"},{"ISSUE_DATE":"Sep 8, 2023 14:21:23","RECEIPT_NO":"85046\/26205","METER_NO":"'07147898576","ACCT_NAME":"LYDIA ELLECHEL","ACCT_NO":"P06633300","VOUCHER_NO":"3237 7644 7714 2820 7353","TOTAL_KWH":"130.3","TOTAL_VALUE":"$39.60"},{"ISSUE_DATE":"Sep 8, 2023 14:21:35","RECEIPT_NO":"85046\/26206","METER_NO":"'07144534380","ACCT_NAME":"EMIKO BAULECHONG & MARGIE BLELAI","ACCT_NO":"P06590400","VOUCHER_NO":"3075 8509 2522 0268 3674","TOTAL_KWH":"150.0","TOTAL_VALUE":"$39.60"},{"ISSUE_DATE":"Sep 8, 2023 14:21:46","RECEIPT_NO":"85046\/26207","METER_NO":"'07053087628","ACCT_NAME":"MARIA BONA ISIMANG","ACCT_NO":"P06237400","VOUCHER_NO":"3384 8265 3774 7340 3458","TOTAL_KWH":"126.4","TOTAL_VALUE":"$39.60"},{"ISSUE_DATE":"Sep 8, 2023 14:21:56","RECEIPT_NO":"85046\/26208","METER_NO":"'07097963784","ACCT_NAME":"MARK ORRUKEM","ACCT_NO":"P06423200","VOUCHER_NO":"2439 9616 4169 4174 5861","TOTAL_KWH":"132.1","TOTAL_VALUE":"$39.60"},{"ISSUE_DATE":"Sep 8, 2023 14:22:07","RECEIPT_NO":"85046\/26209","METER_NO":"'07101016231","ACCT_NAME":"URRIMCH FRANZ","ACCT_NO":"P06225000","VOUCHER_NO":"5765 1225 2022 0101 9111","TOTAL_KWH":"132.1","TOTAL_VALUE":"$39.60"},{"ISSUE_DATE":"Sep 8, 2023 14:22:20","RECEIPT_NO":"85046\/26210","METER_NO":"'07147910991","ACCT_NAME":"MCKINLEY SAMUEL","ACCT_NO":"P06401500","VOUCHER_NO":"3200 4649 5306 6004 3267","TOTAL_KWH":"150.0","TOTAL_VALUE":"$39.60"},{"ISSUE_DATE":"Sep 8, 2023 14:22:35","RECEIPT_NO":"85046\/26211","METER_NO":"'07101015985","ACCT_NAME":"MELONEY SILIANG","ACCT_NO":"P06404400","VOUCHER_NO":"3714 9900 1120 0197 7351","TOTAL_KWH":"130.4","TOTAL_VALUE":"$39.60"},{"ISSUE_DATE":"Sep 8, 2023 14:22:47","RECEIPT_NO":"85046\/26212","METER_NO":"'07147944966","ACCT_NAME":"MENGITIB FRANZ","ACCT_NO":"P06297200","VOUCHER_NO":"5133 5696 2385 7411 6709","TOTAL_KWH":"114.6","TOTAL_VALUE":"$39.60"},{"ISSUE_DATE":"Sep 8, 2023 15:47:47","RECEIPT_NO":"85046\/26213","METER_NO":"'07137644055","ACCT_NAME":"MENRANG MECHAET C\/O CLINDA JAMES","ACCT_NO":"P06556300","VOUCHER_NO":"5659 2211 3482 8573 9404","TOTAL_KWH":"114.6","TOTAL_VALUE":"$39.60"},{"ISSUE_DATE":"Sep 8, 2023 15:48:22","RECEIPT_NO":"85046\/26214","METER_NO":"'07110215006","ACCT_NAME":"MERII UMEDIP","ACCT_NO":"P06533200","VOUCHER_NO":"5617 1854 8406 0776 2859","TOTAL_KWH":"140.9","TOTAL_VALUE":"$37.20"},{"ISSUE_DATE":"Sep 8, 2023 15:48:37","RECEIPT_NO":"85046\/26215","METER_NO":"'07147952084","ACCT_NAME":"MIMOKL SIMEON OR CHELSEA SABURO","ACCT_NO":"P06660900","VOUCHER_NO":"0878 0009 0462 0789 4710","TOTAL_KWH":"114.6","TOTAL_VALUE":"$39.60"},{"ISSUE_DATE":"Sep 8, 2023 15:48:52","RECEIPT_NO":"85046\/26216","METER_NO":"'07101017387","ACCT_NAME":"MITSKO RAFAEL","ACCT_NO":"P06390300","VOUCHER_NO":"6719 6256 8515 6088 0087","TOTAL_KWH":"100.3","TOTAL_VALUE":"$39.60"},{"ISSUE_DATE":"Sep 8, 2023 15:49:07","RECEIPT_NO":"85046\/26217","METER_NO":"'07097967397","ACCT_NAME":"MODESTO PETRUS","ACCT_NO":"P06263600","VOUCHER_NO":"7143 0709 4289 7704 1664","TOTAL_KWH":"100.3","TOTAL_VALUE":"$39.60"},{"ISSUE_DATE":"Sep 8, 2023 15:50:57","RECEIPT_NO":"85046\/26218","METER_NO":"'37263743587","ACCT_NAME":"NAMBERTHA SMAU","ACCT_NO":"P06520900","VOUCHER_NO":"0890 3133 9608 5822 4827","TOTAL_KWH":"123.2","TOTAL_VALUE":"$39.60"},{"ISSUE_DATE":"Sep 8, 2023 15:51:12","RECEIPT_NO":"85046\/26219","METER_NO":"'07147950146","ACCT_NAME":"NGEDRONG AUGUST","ACCT_NO":"P06286700","VOUCHER_NO":"0375 8499 0807 8203 3215","TOTAL_KWH":"132.1","TOTAL_VALUE":"$39.60"},{"ISSUE_DATE":"Sep 8, 2023 15:51:28","RECEIPT_NO":"85046\/26220","METER_NO":"'07050042246","ACCT_NAME":"ARURANG NGIRAIBAKES","ACCT_NO":"P06319700","VOUCHER_NO":"1041 1729 6663 5476 7459","TOTAL_KWH":"150.0","TOTAL_VALUE":"$39.60"},{"ISSUE_DATE":"Sep 8, 2023 15:51:41","RECEIPT_NO":"85046\/26221","METER_NO":"'37263744502","ACCT_NAME":"SEBUU SKIBANG","ACCT_NO":"P06437200","VOUCHER_NO":"1997 2881 3437 2584 6273","TOTAL_KWH":"150.0","TOTAL_VALUE":"$39.60"},{"ISSUE_DATE":"Sep 8, 2023 15:51:53","RECEIPT_NO":"85046\/26222","METER_NO":"'07097963669","ACCT_NAME":"PAUL ANNES","ACCT_NO":"P06421800","VOUCHER_NO":"4359 6539 4393 9966 9537","TOTAL_KWH":"150.0","TOTAL_VALUE":"$39.60"},{"ISSUE_DATE":"Sep 8, 2023 15:52:13","RECEIPT_NO":"85046\/26224","METER_NO":"'07110216145","ACCT_NAME":"PELEFOTI COOPER","ACCT_NO":"P06238600","VOUCHER_NO":"1571 1361 9301 6980 2342","TOTAL_KWH":"114.6","TOTAL_VALUE":"$39.60"},{"ISSUE_DATE":"Sep 8, 2023 15:52:25","RECEIPT_NO":"85046\/26225","METER_NO":"'07144544306","ACCT_NAME":"KISAOL NGIRALOI","ACCT_NO":"P06400200","VOUCHER_NO":"3724 4346 0793 8678 8400","TOTAL_KWH":"132.1","TOTAL_VALUE":"$39.60"},{"ISSUE_DATE":"Sep 8, 2023 15:52:37","RECEIPT_NO":"85046\/26226","METER_NO":"'07101015712","ACCT_NAME":"DAIZIRO NAKAMURA C\/O RAYMOND NAKAMURA","ACCT_NO":"P06400700","VOUCHER_NO":"1936 1269 0903 5195 4547","TOTAL_KWH":"150.0","TOTAL_VALUE":"$39.60"},{"ISSUE_DATE":"Sep 8, 2023 15:53:13","RECEIPT_NO":"85046\/26227","METER_NO":"'07097963222","ACCT_NAME":"ROCKY NGIRASWEI","ACCT_NO":"P06419000","VOUCHER_NO":"5653 6916 5407 1788 5904","TOTAL_KWH":"121.9","TOTAL_VALUE":"$32.19"},{"ISSUE_DATE":"Sep 8, 2023 15:53:27","RECEIPT_NO":"85046\/26228","METER_NO":"'07107716867","ACCT_NAME":"RIKEL NAKAMURA","ACCT_NO":"P06310800","VOUCHER_NO":"0557 0229 2620 5324 1000","TOTAL_KWH":"114.6","TOTAL_VALUE":"$39.60"},{"ISSUE_DATE":"Sep 8, 2023 15:53:40","RECEIPT_NO":"85046\/26229","METER_NO":"'07097969864","ACCT_NAME":"RODNEY ESEBEI","ACCT_NO":"P06473200","VOUCHER_NO":"0288 4191 9613 0650 1104","TOTAL_KWH":"150.0","TOTAL_VALUE":"$39.60"},{"ISSUE_DATE":"Sep 8, 2023 15:53:51","RECEIPT_NO":"85046\/26230","METER_NO":"'07082736112","ACCT_NAME":"ROSE ADELBAI","ACCT_NO":"P06383400","VOUCHER_NO":"7370 8031 5516 4919 0721","TOTAL_KWH":"150.0","TOTAL_VALUE":"$39.60"},{"ISSUE_DATE":"Sep 8, 2023 15:54:04","RECEIPT_NO":"85046\/26231","METER_NO":"'07110218950","ACCT_NAME":"ROXIE NGIRAINGAS","ACCT_NO":"P06382600","VOUCHER_NO":"0209 3592 9582 7309 8183","TOTAL_KWH":"132.1","TOTAL_VALUE":"$39.60"},{"ISSUE_DATE":"Sep 8, 2023 15:54:18","RECEIPT_NO":"85046\/26232","METER_NO":"'07097963677","ACCT_NAME":"SABRINA RECHELULK","ACCT_NO":"P06421700","VOUCHER_NO":"7363 2793 8962 7042 9593","TOTAL_KWH":"114.6","TOTAL_VALUE":"$39.60"},{"ISSUE_DATE":"Sep 8, 2023 15:54:34","RECEIPT_NO":"85046\/26233","METER_NO":"'07057817400","ACCT_NAME":"CLARA SABURO","ACCT_NO":"P06217300","VOUCHER_NO":"2474 5480 8072 6491 0952","TOTAL_KWH":"114.6","TOTAL_VALUE":"$39.60"},{"ISSUE_DATE":"Sep 8, 2023 15:54:47","RECEIPT_NO":"85046\/26234","METER_NO":"'07101017056","ACCT_NAME":"SINESIO SANDEI","ACCT_NO":"P06397800","VOUCHER_NO":"0488 3909 5508 5403 5274","TOTAL_KWH":"114.6","TOTAL_VALUE":"$39.60"},{"ISSUE_DATE":"Sep 8, 2023 15:55:01","RECEIPT_NO":"85046\/26235","METER_NO":"'07097965656","ACCT_NAME":"SINGERU NGIRAMOLAU #8","ACCT_NO":"P06438100","VOUCHER_NO":"1896 2412 6418 2798 0640","TOTAL_KWH":"150.0","TOTAL_VALUE":"$39.60"},{"ISSUE_DATE":"Sep 8, 2023 15:55:43","RECEIPT_NO":"85046\/26236","METER_NO":"'37263737043","ACCT_NAME":"SISKIND ADELBAI","ACCT_NO":"P06193200","VOUCHER_NO":"1147 0338 8527 6634 0501","TOTAL_KWH":"150.0","TOTAL_VALUE":"$39.60"},{"ISSUE_DATE":"Sep 8, 2023 15:57:03","RECEIPT_NO":"85046\/26237","METER_NO":"'37263744510","ACCT_NAME":"ALFONSO NGIRNGOTEL","ACCT_NO":"P06227000","VOUCHER_NO":"0389 0899 7905 4801 0044","TOTAL_KWH":"150.0","TOTAL_VALUE":"$39.60"},{"ISSUE_DATE":"Sep 8, 2023 15:57:15","RECEIPT_NO":"85046\/26238","METER_NO":"'07110218869","ACCT_NAME":"SUZETTE MARYLOU RIDEP","ACCT_NO":"P06526800","VOUCHER_NO":"3821 8759 4483 3647 7817","TOTAL_KWH":"138.6","TOTAL_VALUE":"$39.60"},{"ISSUE_DATE":"Sep 8, 2023 15:57:30","RECEIPT_NO":"85046\/26239","METER_NO":"'07144545618","ACCT_NAME":"TADAO SKEBONG #2","ACCT_NO":"P06607300","VOUCHER_NO":"3231 6776 7671 0124 4154","TOTAL_KWH":"138.6","TOTAL_VALUE":"$39.60"},{"ISSUE_DATE":"Sep 8, 2023 15:57:41","RECEIPT_NO":"85046\/26240","METER_NO":"'07050042477","ACCT_NAME":"TAKEMITS OBEKETANG","ACCT_NO":"P06320200","VOUCHER_NO":"0997 5113 7481 8388 8473","TOTAL_KWH":"150.0","TOTAL_VALUE":"$39.60"},{"ISSUE_DATE":"Sep 8, 2023 15:58:24","RECEIPT_NO":"85046\/26241","METER_NO":"'07137643792","ACCT_NAME":"TAKEO RENGIIL","ACCT_NO":"P06540100","VOUCHER_NO":"3847 2003 3585 5422 9561","TOTAL_KWH":"150.0","TOTAL_VALUE":"$39.60"},{"ISSUE_DATE":"Sep 8, 2023 15:58:36","RECEIPT_NO":"85046\/26242","METER_NO":"'07110878670","ACCT_NAME":"TANI ICHIRO","ACCT_NO":"P06581500","VOUCHER_NO":"5952 2544 1887 5155 5655","TOTAL_KWH":"150.0","TOTAL_VALUE":"$39.60"},{"ISSUE_DATE":"Sep 8, 2023 15:58:49","RECEIPT_NO":"85046\/26243","METER_NO":"'07147932193","ACCT_NAME":"TELEBADEL BAULECHONG","ACCT_NO":"P06679400","VOUCHER_NO":"5160 2371 9965 3966 1097","TOTAL_KWH":"114.6","TOTAL_VALUE":"$39.60"},{"ISSUE_DATE":"Sep 8, 2023 15:59:01","RECEIPT_NO":"85046\/26244","METER_NO":"'07147910819","ACCT_NAME":"THELBOI BAIEI","ACCT_NO":"P06512800","VOUCHER_NO":"0856 0126 7909 8990 9945","TOTAL_KWH":"150.0","TOTAL_VALUE":"$39.60"},{"ISSUE_DATE":"Sep 8, 2023 15:59:14","RECEIPT_NO":"85046\/26245","METER_NO":"'07097967819","ACCT_NAME":"SILAS KINGZIO","ACCT_NO":"P06193700","VOUCHER_NO":"3180 3896 2072 3522 4831","TOTAL_KWH":"150.0","TOTAL_VALUE":"$39.60"},{"ISSUE_DATE":"Sep 8, 2023 15:59:24","RECEIPT_NO":"85046\/26246","METER_NO":"'07057817335","ACCT_NAME":"TOSHIWO TAKATARO RESIDENCE","ACCT_NO":"P06574100","VOUCHER_NO":"4987 5133 8205 3955 5375","TOTAL_KWH":"150.0","TOTAL_VALUE":"$39.60"},{"ISSUE_DATE":"Sep 8, 2023 15:59:34","RECEIPT_NO":"85046\/26247","METER_NO":"'07144536500","ACCT_NAME":"TRIOLLA UEHARA","ACCT_NO":"P06591100","VOUCHER_NO":"5498 1986 1509 3097 1689","TOTAL_KWH":"114.6","TOTAL_VALUE":"$39.60"},{"ISSUE_DATE":"Sep 8, 2023 15:59:45","RECEIPT_NO":"85046\/26248","METER_NO":"'07057817889","ACCT_NAME":"ROSELLA Y. MASAMI","ACCT_NO":"P06253900","VOUCHER_NO":"5625 1755 9902 7957 8183","TOTAL_KWH":"114.6","TOTAL_VALUE":"$39.60"},{"ISSUE_DATE":"Sep 8, 2023 16:00:06","RECEIPT_NO":"85046\/26249","METER_NO":"'07082734596","ACCT_NAME":"UCHELLAS NGIRACHITEI","ACCT_NO":"P06286200","VOUCHER_NO":"2531 1651 4655 0098 8194","TOTAL_KWH":"74.0","TOTAL_VALUE":"$19.54"},{"ISSUE_DATE":"Sep 8, 2023 16:00:21","RECEIPT_NO":"85046\/26250","METER_NO":"'07097966787","ACCT_NAME":"VALERIA RDIALL","ACCT_NO":"P06449300","VOUCHER_NO":"2592 3025 4845 3376 9220","TOTAL_KWH":"150.0","TOTAL_VALUE":"$39.60"},{"ISSUE_DATE":"Sep 8, 2023 16:00:33","RECEIPT_NO":"85046\/26251","METER_NO":"'07144545725","ACCT_NAME":"VANILLY WILLIAM","ACCT_NO":"P06609500","VOUCHER_NO":"5994 6927 0779 8745 4376","TOTAL_KWH":"130.4","TOTAL_VALUE":"$39.60"},{"ISSUE_DATE":"Sep 8, 2023 16:00:43","RECEIPT_NO":"85046\/26252","METER_NO":"'07144544850","ACCT_NAME":"VERONICA TELIU","ACCT_NO":"P06611800","VOUCHER_NO":"0408 8215 8060 6381 1259","TOTAL_KWH":"150.0","TOTAL_VALUE":"$39.60"},{"ISSUE_DATE":"Sep 8, 2023 16:00:52","RECEIPT_NO":"85046\/26253","METER_NO":"'07107716958","ACCT_NAME":"VERONICA UMEDIP","ACCT_NO":"P06291100","VOUCHER_NO":"0791 3576 9167 3152 4464","TOTAL_KWH":"114.6","TOTAL_VALUE":"$39.60"},{"ISSUE_DATE":"Sep 8, 2023 16:01:01","RECEIPT_NO":"85046\/26254","METER_NO":"'07077091978","ACCT_NAME":"VIDA IMEONG","ACCT_NO":"P06337900","VOUCHER_NO":"6584 3279 0125 7646 2698","TOTAL_KWH":"114.6","TOTAL_VALUE":"$39.60"},{"ISSUE_DATE":"Sep 8, 2023 16:02:00","RECEIPT_NO":"85046\/26255","METER_NO":"'07097964923","ACCT_NAME":"WALTER MARIUR","ACCT_NO":"P06437600","VOUCHER_NO":"4879 7410 6305 9173 3063","TOTAL_KWH":"114.6","TOTAL_VALUE":"$39.60"},{"ISSUE_DATE":"Sep 8, 2023 16:02:59","RECEIPT_NO":"85046\/26256","METER_NO":"'07107718657","ACCT_NAME":"ERNEST ONGIDOBEL ROOM #2","ACCT_NO":"P06520600","VOUCHER_NO":"1117 7062 5230 6182 2500","TOTAL_KWH":"114.6","TOTAL_VALUE":"$39.60"},{"ISSUE_DATE":"Sep 8, 2023 16:03:31","RECEIPT_NO":"85046\/26257","METER_NO":"'37263743611","ACCT_NAME":"WILSON SELBART","ACCT_NO":"P06543800","VOUCHER_NO":"5429 6976 9474 7050 4642","TOTAL_KWH":"150.0","TOTAL_VALUE":"$39.60"},{"ISSUE_DATE":"Sep 8, 2023 16:03:45","RECEIPT_NO":"85046\/26258","METER_NO":"'07077091739","ACCT_NAME":"YANANGI MATUL","ACCT_NO":"P06340600","VOUCHER_NO":"6742 9963 7481 1021 3540","TOTAL_KWH":"114.6","TOTAL_VALUE":"$39.60"},{"ISSUE_DATE":"Sep 8, 2023 16:03:57","RECEIPT_NO":"85046\/26259","METER_NO":"'07147913318","ACCT_NAME":"YOHEI MERUR","ACCT_NO":"P06240500","VOUCHER_NO":"0178 4003 7801 0699 5666","TOTAL_KWH":"114.6","TOTAL_VALUE":"$39.60"},{"ISSUE_DATE":"Sep 8, 2023 16:04:09","RECEIPT_NO":"85046\/26260","METER_NO":"'07097968940","ACCT_NAME":"YUZIRO KLOULUBAK","ACCT_NO":"P06467200","VOUCHER_NO":"7154 7545 5419 1242 2996","TOTAL_KWH":"100.3","TOTAL_VALUE":"$39.60"},{"ISSUE_DATE":"Sep 8, 2023 16:04:24","RECEIPT_NO":"85046\/26261","METER_NO":"'07050042675","ACCT_NAME":"LEEMANSKY BLAU","ACCT_NO":"P06566400","VOUCHER_NO":"3834 8466 3498 8717 3059","TOTAL_KWH":"114.6","TOTAL_VALUE":"$39.60"},{"ISSUE_DATE":"Sep 8, 2023 16:04:39","RECEIPT_NO":"85046\/26262","METER_NO":"'07097965359","ACCT_NAME":"MERCY RAMARUI","ACCT_NO":"P06435000","VOUCHER_NO":"2601 6430 7699 8978 7063","TOTAL_KWH":"114.6","TOTAL_VALUE":"$39.60"},{"ISSUE_DATE":"Sep 8, 2023 16:04:54","RECEIPT_NO":"85046\/26263","METER_NO":"'07110218679","ACCT_NAME":"DILMAI HARUO","ACCT_NO":"P06532100","VOUCHER_NO":"0652 4682 5763 5181 6501","TOTAL_KWH":"150.0","TOTAL_VALUE":"$39.60"},{"ISSUE_DATE":"Sep 8, 2023 16:05:04","RECEIPT_NO":"85046\/26264","METER_NO":"'07147952225","ACCT_NAME":"SOLOMON MARINO 2","ACCT_NO":"P06673600","VOUCHER_NO":"7047 2679 3250 8387 7280","TOTAL_KWH":"150.0","TOTAL_VALUE":"$39.60"},{"ISSUE_DATE":"Sep 8, 2023 16:05:14","RECEIPT_NO":"85046\/26265","METER_NO":"'07147945500","ACCT_NAME":"EMORY MESUBED","ACCT_NO":"P06678500","VOUCHER_NO":"1758 1185 8279 1333 4828","TOTAL_KWH":"114.6","TOTAL_VALUE":"$39.60"},{"ISSUE_DATE":"Sep 8, 2023 16:05:24","RECEIPT_NO":"85046\/26266","METER_NO":"'07097971266","ACCT_NAME":"THOMAS REMENGESAU","ACCT_NO":"P06484200","VOUCHER_NO":"3516 1700 1000 1365 7327","TOTAL_KWH":"118.8","TOTAL_VALUE":"$39.60"},{"ISSUE_DATE":"Sep 8, 2023 16:05:40","RECEIPT_NO":"85046\/26267","METER_NO":"'37263744643","ACCT_NAME":"FELIX JR. MEREB","ACCT_NO":"P06405500","VOUCHER_NO":"5356 5116 1233 9923 3530","TOTAL_KWH":"150.0","TOTAL_VALUE":"$39.60"},{"ISSUE_DATE":"Sep 8, 2023 16:05:54","RECEIPT_NO":"85046\/26268","METER_NO":"'07101017049","ACCT_NAME":"FUANA RUDIMCH","ACCT_NO":"P06397400","VOUCHER_NO":"2610 3129 9166 9206 3892","TOTAL_KWH":"130.4","TOTAL_VALUE":"$39.60"},{"ISSUE_DATE":"Sep 8, 2023 16:06:08","RECEIPT_NO":"85046\/26269","METER_NO":"'07107715513","ACCT_NAME":"ASHLEY HENRY","ACCT_NO":"P06492400","VOUCHER_NO":"0164 0904 7999 8463 5128","TOTAL_KWH":"150.0","TOTAL_VALUE":"$39.60"},{"ISSUE_DATE":"Sep 8, 2023 16:06:24","RECEIPT_NO":"85046\/26270","METER_NO":"'07097961945","ACCT_NAME":"ULAI DEMEI #3","ACCT_NO":"P06407400","VOUCHER_NO":"0804 1256 7881 7590 2121","TOTAL_KWH":"114.6","TOTAL_VALUE":"$39.60"},{"ISSUE_DATE":"Sep 8, 2023 16:06:37","RECEIPT_NO":"85046\/26271","METER_NO":"'07057780038","ACCT_NAME":"FRANCIS S. ALONZ","ACCT_NO":"P06296200","VOUCHER_NO":"5153 4830 7303 0357 9210","TOTAL_KWH":"150.0","TOTAL_VALUE":"$39.60"},{"ISSUE_DATE":"Sep 8, 2023 16:06:48","RECEIPT_NO":"85046\/26272","METER_NO":"'07147949155","ACCT_NAME":"STARGEL MAMIS","ACCT_NO":"P06244800","VOUCHER_NO":"0701 8982 2841 5439 7122","TOTAL_KWH":"132.1","TOTAL_VALUE":"$39.60"},{"ISSUE_DATE":"Sep 8, 2023 16:07:01","RECEIPT_NO":"85046\/26273","METER_NO":"'07147898360","ACCT_NAME":"IKREBAI BLESAM","ACCT_NO":"P06630500","VOUCHER_NO":"5797 3340 5032 3939 1060","TOTAL_KWH":"114.6","TOTAL_VALUE":"$39.60"},{"ISSUE_DATE":"Sep 8, 2023 16:07:13","RECEIPT_NO":"85046\/26274","METER_NO":"'07110879827","ACCT_NAME":"SEIICHI RIUMD","ACCT_NO":"P06586600","VOUCHER_NO":"3039 1607 9284 2272 4042","TOTAL_KWH":"150.0","TOTAL_VALUE":"$39.60"},{"ISSUE_DATE":"Sep 8, 2023 16:07:24","RECEIPT_NO":"85046\/26275","METER_NO":"'07110917759","ACCT_NAME":"JENNIFER KUMANGAI","ACCT_NO":"P06544200","VOUCHER_NO":"6355 3561 4736 0048 2657","TOTAL_KWH":"132.1","TOTAL_VALUE":"$39.60"},{"ISSUE_DATE":"Sep 8, 2023 16:07:36","RECEIPT_NO":"85046\/26276","METER_NO":"'07147951177","ACCT_NAME":"PRINCE IDELKEI","ACCT_NO":"P06648800","VOUCHER_NO":"0909 9806 7754 2485 3155","TOTAL_KWH":"129.5","TOTAL_VALUE":"$39.60"},{"ISSUE_DATE":"Sep 8, 2023 16:07:53","RECEIPT_NO":"85046\/26277","METER_NO":"'07050043079","ACCT_NAME":"HANA INGAIS","ACCT_NO":"P06325800","VOUCHER_NO":"6204 1721 6354 2636 8550","TOTAL_KWH":"114.6","TOTAL_VALUE":"$39.60"},{"ISSUE_DATE":"Sep 8, 2023 16:08:22","RECEIPT_NO":"85046\/26278","METER_NO":"'07144544918","ACCT_NAME":"TCHUZIE & SHERRYANN TADAO","ACCT_NO":"P06613400","VOUCHER_NO":"1870 0501 1558 6653 8225","TOTAL_KWH":"150.0","TOTAL_VALUE":"$39.60"},{"ISSUE_DATE":"Sep 8, 2023 16:08:35","RECEIPT_NO":"85046\/26279","METER_NO":"'07053088816","ACCT_NAME":"LIZETTE NGIRAIBAI","ACCT_NO":"P06214300","VOUCHER_NO":"0387 8221 6811 8410 4164","TOTAL_KWH":"114.6","TOTAL_VALUE":"$39.60"},{"ISSUE_DATE":"Sep 8, 2023 16:08:46","RECEIPT_NO":"85046\/26280","METER_NO":"'07107718244","ACCT_NAME":"AILEEN TECHUR","ACCT_NO":"P06510600","VOUCHER_NO":"6999 0754 9443 6237 6571","TOTAL_KWH":"150.0","TOTAL_VALUE":"$39.60"},{"ISSUE_DATE":"Sep 8, 2023 16:08:58","RECEIPT_NO":"85046\/26281","METER_NO":"'07110214876","ACCT_NAME":"JULIET PEDRO","ACCT_NO":"P06524600","VOUCHER_NO":"1338 1848 3211 8617 4994","TOTAL_KWH":"123.2","TOTAL_VALUE":"$39.60"},{"ISSUE_DATE":"Sep 8, 2023 16:09:10","RECEIPT_NO":"85046\/26282","METER_NO":"'07097966555","ACCT_NAME":"EDWARD TADAO","ACCT_NO":"P06447000","VOUCHER_NO":"6438 9335 6303 3120 1994","TOTAL_KWH":"130.4","TOTAL_VALUE":"$39.60"},{"ISSUE_DATE":"Sep 8, 2023 16:09:25","RECEIPT_NO":"85046\/26283","METER_NO":"'07097962760","ACCT_NAME":"RIEGERT N. BLELAI","ACCT_NO":"P06415600","VOUCHER_NO":"5653 2510 7348 8260 1122","TOTAL_KWH":"150.0","TOTAL_VALUE":"$39.60"},{"ISSUE_DATE":"Sep 8, 2023 16:09:37","RECEIPT_NO":"85046\/26284","METER_NO":"'07147945344","ACCT_NAME":"MITSUE TORIBIONG","ACCT_NO":"P06653100","VOUCHER_NO":"2626 9297 9129 0670 9317","TOTAL_KWH":"114.6","TOTAL_VALUE":"$39.60"},{"ISSUE_DATE":"Sep 8, 2023 16:09:49","RECEIPT_NO":"85046\/26285","METER_NO":"'07097963842","ACCT_NAME":"ISAAC STEPHANUS","ACCT_NO":"P06424100","VOUCHER_NO":"6522 8454 1880 3076 4986","TOTAL_KWH":"132.1","TOTAL_VALUE":"$39.60"},{"ISSUE_DATE":"Sep 8, 2023 16:10:02","RECEIPT_NO":"85046\/26286","METER_NO":"'07050042469","ACCT_NAME":"HARUKO DEMEI","ACCT_NO":"P06320300","VOUCHER_NO":"5010 8765 1550 7319 3625","TOTAL_KWH":"132.1","TOTAL_VALUE":"$39.60"},{"ISSUE_DATE":"Sep 8, 2023 16:10:12","RECEIPT_NO":"85046\/26287","METER_NO":"'07082740171","ACCT_NAME":"DILBELAU DILUTAOCH","ACCT_NO":"P06377800","VOUCHER_NO":"2376 5208 7685 0505 5038","TOTAL_KWH":"150.0","TOTAL_VALUE":"$39.60"},{"ISSUE_DATE":"Sep 8, 2023 16:10:21","RECEIPT_NO":"85046\/26288","METER_NO":"'07050042436","ACCT_NAME":"JOHNNY MONGAMI","ACCT_NO":"P06320500","VOUCHER_NO":"4767 3792 5577 1763 6962","TOTAL_KWH":"117.5","TOTAL_VALUE":"$39.60"},{"ISSUE_DATE":"Sep 8, 2023 16:10:33","RECEIPT_NO":"85046\/26289","METER_NO":"'07147951318","ACCT_NAME":"KERUNGIL M. AUGUSTINE","ACCT_NO":"P06657500","VOUCHER_NO":"6361 0064 9917 0120 4138","TOTAL_KWH":"114.6","TOTAL_VALUE":"$39.60"},{"ISSUE_DATE":"Sep 8, 2023 16:10:44","RECEIPT_NO":"85046\/26290","METER_NO":"'07097965078","ACCT_NAME":"SABA TEWID","ACCT_NO":"P06433500","VOUCHER_NO":"3437 1230 0142 6794 9111","TOTAL_KWH":"114.6","TOTAL_VALUE":"$39.60"},{"ISSUE_DATE":"Sep 8, 2023 16:10:56","RECEIPT_NO":"85046\/26291","METER_NO":"'07097970904","ACCT_NAME":"JESSE SUMOR","ACCT_NO":"P06502100","VOUCHER_NO":"1257 1608 8481 8519 1679","TOTAL_KWH":"114.6","TOTAL_VALUE":"$39.60"},{"ISSUE_DATE":"Sep 8, 2023 16:11:08","RECEIPT_NO":"85046\/26292","METER_NO":"'07110916975","ACCT_NAME":"MARGARITA MENGESBUUCH","ACCT_NO":"P06225500","VOUCHER_NO":"6624 0510 8247 1082 7010","TOTAL_KWH":"150.0","TOTAL_VALUE":"$39.60"},{"ISSUE_DATE":"Sep 8, 2023 16:11:19","RECEIPT_NO":"85046\/26293","METER_NO":"'07097966670","ACCT_NAME":"FERNANDO KEWII","ACCT_NO":"P06448600","VOUCHER_NO":"0598 0040 0799 4171 7878","TOTAL_KWH":"150.0","TOTAL_VALUE":"$39.60"},{"ISSUE_DATE":"Sep 8, 2023 16:11:31","RECEIPT_NO":"85046\/26294","METER_NO":"'07097967470","ACCT_NAME":"JOSHUA INGAIS","ACCT_NO":"P06454200","VOUCHER_NO":"3959 3416 6314 3608 8323","TOTAL_KWH":"114.6","TOTAL_VALUE":"$39.60"},{"ISSUE_DATE":"Sep 8, 2023 16:11:41","RECEIPT_NO":"85046\/26295","METER_NO":"'07050106595","ACCT_NAME":"MARCELUS TECHUR","ACCT_NO":"P06353300","VOUCHER_NO":"4798 9884 0968 6934 8662","TOTAL_KWH":"150.0","TOTAL_VALUE":"$39.60"},{"ISSUE_DATE":"Sep 8, 2023 16:11:52","RECEIPT_NO":"85046\/26296","METER_NO":"'07110218943","ACCT_NAME":"VERNA OBAK","ACCT_NO":"P06532500","VOUCHER_NO":"3039 5601 5988 8052 2585","TOTAL_KWH":"114.6","TOTAL_VALUE":"$39.60"},{"ISSUE_DATE":"Sep 8, 2023 16:12:02","RECEIPT_NO":"85046\/26297","METER_NO":"'07147916204","ACCT_NAME":"CLINT MADRACHELUIB","ACCT_NO":"P06704800","VOUCHER_NO":"2456 1717 6583 0108 2825","TOTAL_KWH":"114.6","TOTAL_VALUE":"$39.60"},{"ISSUE_DATE":"Sep 8, 2023 16:12:50","RECEIPT_NO":"85046\/26298","METER_NO":"'07053087461","ACCT_NAME":"MERLIN BENJAMIN","ACCT_NO":"P06238700","VOUCHER_NO":"2395 2332 9092 2388 5169","TOTAL_KWH":"150.0","TOTAL_VALUE":"$39.60"},{"ISSUE_DATE":"Sep 8, 2023 16:13:01","RECEIPT_NO":"85046\/26299","METER_NO":"'07101017403","ACCT_NAME":"SHEILA SILMAI","ACCT_NO":"P06390100","VOUCHER_NO":"0173 9581 5915 6816 8908","TOTAL_KWH":"114.6","TOTAL_VALUE":"$39.60"},{"ISSUE_DATE":"Sep 8, 2023 16:13:14","RECEIPT_NO":"85046\/26300","METER_NO":"'07097969187","ACCT_NAME":"DELFITHA DELEMEL","ACCT_NO":"P06469000","VOUCHER_NO":"4591 4448 2143 3591 8883","TOTAL_KWH":"114.6","TOTAL_VALUE":"$39.60"},{"ISSUE_DATE":"Sep 8, 2023 16:13:25","RECEIPT_NO":"85046\/26301","METER_NO":"'07097963529","ACCT_NAME":"YASKO LEBAL STASH RENGUUL","ACCT_NO":"P06421400","VOUCHER_NO":"3032 3488 5820 7434 4246","TOTAL_KWH":"114.6","TOTAL_VALUE":"$39.60"},{"ISSUE_DATE":"Sep 8, 2023 16:16:28","RECEIPT_NO":"85046\/26302","METER_NO":"'07110879629","ACCT_NAME":"RAINA BAILAS","ACCT_NO":"P06585300","VOUCHER_NO":"7105 1222 8879 9148 8149","TOTAL_KWH":"150.0","TOTAL_VALUE":"$39.60"},{"ISSUE_DATE":"Sep 8, 2023 16:16:42","RECEIPT_NO":"85046\/26303","METER_NO":"'07147951086","ACCT_NAME":"ANDREA SABURO","ACCT_NO":"P06219700","VOUCHER_NO":"6978 5565 5624 2577 8238","TOTAL_KWH":"114.6","TOTAL_VALUE":"$39.60"},{"ISSUE_DATE":"Sep 8, 2023 16:16:59","RECEIPT_NO":"85046\/26304","METER_NO":"'07110879900","ACCT_NAME":"ANTHONIO IYECHAD","ACCT_NO":"P06587000","VOUCHER_NO":"1841 7247 5085 6726 2003","TOTAL_KWH":"150.0","TOTAL_VALUE":"$39.60"},{"ISSUE_DATE":"Sep 8, 2023 16:17:26","RECEIPT_NO":"85046\/26305","METER_NO":"'07147952233","ACCT_NAME":"PUANANI PEDRO","ACCT_NO":"P06673700","VOUCHER_NO":"1590 1235 8673 3106 3025","TOTAL_KWH":"150.0","TOTAL_VALUE":"$39.60"},{"ISSUE_DATE":"Sep 8, 2023 16:17:38","RECEIPT_NO":"85046\/26306","METER_NO":"'07147915503","ACCT_NAME":"BUNGELLONG TEBELAK","ACCT_NO":"P06705200","VOUCHER_NO":"1507 2206 3993 8896 9898","TOTAL_KWH":"114.6","TOTAL_VALUE":"$39.60"},{"ISSUE_DATE":"Sep 8, 2023 16:17:51","RECEIPT_NO":"85046\/26307","METER_NO":"'07107717550","ACCT_NAME":"ANITA TEBLAK AND SECHALKUI NGIRNGESECHEI","ACCT_NO":"P06516500","VOUCHER_NO":"4280 4243 5136 5507 1389","TOTAL_KWH":"143.4","TOTAL_VALUE":"$39.60"},{"ISSUE_DATE":"Sep 8, 2023 16:18:40","RECEIPT_NO":"85046\/26308","METER_NO":"'07097968734","ACCT_NAME":"CHALETTE NGIRAIECHOL","ACCT_NO":"P06465400","VOUCHER_NO":"4329 5455 7283 7860 1881","TOTAL_KWH":"150.0","TOTAL_VALUE":"$39.60"},{"ISSUE_DATE":"Sep 8, 2023 16:19:09","RECEIPT_NO":"85046\/26309","METER_NO":"'07144537466","ACCT_NAME":"STEPHEN SANTOS","ACCT_NO":"P06597000","VOUCHER_NO":"4307 4405 9538 9405 1616","TOTAL_KWH":"150.0","TOTAL_VALUE":"$39.60"},{"ISSUE_DATE":"Sep 8, 2023 16:19:26","RECEIPT_NO":"85046\/26310","METER_NO":"'07147945294","ACCT_NAME":"APRIL WATANABE","ACCT_NO":"P06301100","VOUCHER_NO":"6622 9585 4645 9794 7769","TOTAL_KWH":"132.1","TOTAL_VALUE":"$39.60"},{"ISSUE_DATE":"Sep 8, 2023 16:19:40","RECEIPT_NO":"85046\/26311","METER_NO":"'07057779865","ACCT_NAME":"CHARLENE MERSAI","ACCT_NO":"P06572400","VOUCHER_NO":"4628 1378 4427 5883 6277","TOTAL_KWH":"150.0","TOTAL_VALUE":"$39.60"},{"ISSUE_DATE":"Sep 8, 2023 16:19:51","RECEIPT_NO":"85046\/26312","METER_NO":"'07097966738","ACCT_NAME":"ESANG OLKERIIL","ACCT_NO":"P06447100","VOUCHER_NO":"0639 9622 0885 0347 2264","TOTAL_KWH":"114.6","TOTAL_VALUE":"$39.60"},{"ISSUE_DATE":"Sep 8, 2023 16:20:04","RECEIPT_NO":"85046\/26313","METER_NO":"'07082740023","ACCT_NAME":"BENJAMIN MASTERS","ACCT_NO":"P06374000","VOUCHER_NO":"1318 8775 0048 9170 4408","TOTAL_KWH":"114.6","TOTAL_VALUE":"$39.60"},{"ISSUE_DATE":"Sep 8, 2023 16:20:17","RECEIPT_NO":"85046\/26314","METER_NO":"'07110214736","ACCT_NAME":"JUSTINO MECHAET","ACCT_NO":"P06535700","VOUCHER_NO":"1446 7426 4876 4014 7852","TOTAL_KWH":"150.0","TOTAL_VALUE":"$39.60"},{"ISSUE_DATE":"Sep 8, 2023 16:21:01","RECEIPT_NO":"85046\/26315","METER_NO":"'07097964394","ACCT_NAME":"ALEXIS KINTO","ACCT_NO":"P06428100","VOUCHER_NO":"6725 6546 1902 2182 7999","TOTAL_KWH":"133.6","TOTAL_VALUE":"$39.60"},{"ISSUE_DATE":"Sep 8, 2023 16:23:54","RECEIPT_NO":"85046\/26316","METER_NO":"'07147910058","ACCT_NAME":"FELIX MEREB","ACCT_NO":"P06696500","VOUCHER_NO":"4154 5683 6558 7472 0185","TOTAL_KWH":"150.0","TOTAL_VALUE":"$39.60"},{"ISSUE_DATE":"Sep 8, 2023 16:24:13","RECEIPT_NO":"85046\/26317","METER_NO":"'07110879793","ACCT_NAME":"REMOKET MARKUB","ACCT_NO":"P06588700","VOUCHER_NO":"4278 6501 3945 7343 5058","TOTAL_KWH":"150.0","TOTAL_VALUE":"$39.60"},{"ISSUE_DATE":"Sep 8, 2023 16:24:30","RECEIPT_NO":"85046\/26318","METER_NO":"'07097968676","ACCT_NAME":"MARS OLKERIIL","ACCT_NO":"P06464700","VOUCHER_NO":"6183 7045 4418 9998 4928","TOTAL_KWH":"150.0","TOTAL_VALUE":"$39.60"},{"ISSUE_DATE":"Sep 8, 2023 16:24:43","RECEIPT_NO":"85046\/26319","METER_NO":"'07147932599","ACCT_NAME":"DAVIS THOME","ACCT_NO":"P06675400","VOUCHER_NO":"7139 4526 0760 3466 4505","TOTAL_KWH":"114.6","TOTAL_VALUE":"$39.60"},{"ISSUE_DATE":"Sep 8, 2023 16:30:54","RECEIPT_NO":"85046\/26320","METER_NO":"'07057818655","ACCT_NAME":"JASON BREL JR.","ACCT_NO":"P06269600","VOUCHER_NO":"0731 2355 6345 7075 5168","TOTAL_KWH":"150.0","TOTAL_VALUE":"$39.60"},{"ISSUE_DATE":"Sep 8, 2023 16:31:08","RECEIPT_NO":"85046\/26321","METER_NO":"'07144537508","ACCT_NAME":"BIEB ILLEMELONG","ACCT_NO":"P06598100","VOUCHER_NO":"4571 0967 2652 1544 2353","TOTAL_KWH":"130.4","TOTAL_VALUE":"$39.60"},{"ISSUE_DATE":"Sep 8, 2023 16:31:26","RECEIPT_NO":"85046\/26322","METER_NO":"'07144537805","ACCT_NAME":"ROBIN NGIRALMUUT","ACCT_NO":"P06598700","VOUCHER_NO":"0940 6505 5506 0955 0961","TOTAL_KWH":"150.0","TOTAL_VALUE":"$39.60"},{"ISSUE_DATE":"Sep 8, 2023 16:31:45","RECEIPT_NO":"85046\/26323","METER_NO":"'07097967967","ACCT_NAME":"OMEBAEL BASILIUS ","ACCT_NO":"P06459000","VOUCHER_NO":"4638 9730 6805 2064 3418","TOTAL_KWH":"114.6","TOTAL_VALUE":"$39.60"},{"ISSUE_DATE":"Sep 8, 2023 16:31:58","RECEIPT_NO":"85046\/26324","METER_NO":"'07147916402","ACCT_NAME":"OLSUDONG OIKANG","ACCT_NO":"P06292300","VOUCHER_NO":"3103 9808 5932 1174 9652","TOTAL_KWH":"114.6","TOTAL_VALUE":"$39.60"},{"ISSUE_DATE":"Sep 8, 2023 16:32:09","RECEIPT_NO":"85046\/26325","METER_NO":"'07097971142","ACCT_NAME":"YOSIO NGIRAINGAS","ACCT_NO":"P06483400","VOUCHER_NO":"7226 9745 9206 3531 5712","TOTAL_KWH":"150.0","TOTAL_VALUE":"$39.60"},{"ISSUE_DATE":"Sep 8, 2023 16:32:26","RECEIPT_NO":"85046\/26326","METER_NO":"'07144534273","ACCT_NAME":"LUCIUS BEKETAUT","ACCT_NO":"P06589500","VOUCHER_NO":"7280 4170 8739 0303 2359","TOTAL_KWH":"114.6","TOTAL_VALUE":"$39.60"},{"ISSUE_DATE":"Sep 8, 2023 16:32:46","RECEIPT_NO":"85046\/26327","METER_NO":"'07147944826","ACCT_NAME":"NERLINA MEREB","ACCT_NO":"P06367300","VOUCHER_NO":"6231 3627 8856 3988 4270","TOTAL_KWH":"114.6","TOTAL_VALUE":"$39.60"},{"ISSUE_DATE":"Sep 8, 2023 16:32:58","RECEIPT_NO":"85046\/26328","METER_NO":"'07147948306","ACCT_NAME":"JUSLEE MAUI","ACCT_NO":"P06673000","VOUCHER_NO":"0094 8029 0762 4322 6479","TOTAL_KWH":"114.6","TOTAL_VALUE":"$39.60"},{"ISSUE_DATE":"Sep 8, 2023 16:38:46","RECEIPT_NO":"85046\/26329","METER_NO":"'07147899111","ACCT_NAME":"MERIBAL EWATEL 2","ACCT_NO":"P06639000","VOUCHER_NO":"1135 7706 8583 8364 8653","TOTAL_KWH":"150.0","TOTAL_VALUE":"$39.60"},{"ISSUE_DATE":"Sep 8, 2023 16:39:00","RECEIPT_NO":"85046\/26330","METER_NO":"'07137643362","ACCT_NAME":"MARIA SANTOS","ACCT_NO":"P06216200","VOUCHER_NO":"2306 3409 6230 5917 2061","TOTAL_KWH":"130.3","TOTAL_VALUE":"$39.60"},{"ISSUE_DATE":"Sep 8, 2023 16:39:13","RECEIPT_NO":"85046\/26331","METER_NO":"'07147899053","ACCT_NAME":"PETER MIKEL","ACCT_NO":"P06635800","VOUCHER_NO":"1365 0485 1542 2465 9477","TOTAL_KWH":"114.6","TOTAL_VALUE":"$39.60"},{"ISSUE_DATE":"Sep 8, 2023 16:39:25","RECEIPT_NO":"85046\/26332","METER_NO":"'07097968262","ACCT_NAME":"KERNGEL TESEI","ACCT_NO":"P06345900","VOUCHER_NO":"0879 8156 6557 8369 0352","TOTAL_KWH":"150.0","TOTAL_VALUE":"$39.60"},{"ISSUE_DATE":"Sep 8, 2023 16:39:37","RECEIPT_NO":"85046\/26333","METER_NO":"'07147950740","ACCT_NAME":"STEVENSON NGIRAKED","ACCT_NO":"P06305200","VOUCHER_NO":"5522 3776 6305 9474 6196","TOTAL_KWH":"150.0","TOTAL_VALUE":"$39.60"},{"ISSUE_DATE":"Sep 8, 2023 16:39:49","RECEIPT_NO":"85046\/26334","METER_NO":"'07147899392","ACCT_NAME":"RISAO BAUSOCH","ACCT_NO":"P06641100","VOUCHER_NO":"0254 0485 0682 2910 3218","TOTAL_KWH":"114.6","TOTAL_VALUE":"$39.60"},{"ISSUE_DATE":"Sep 8, 2023 16:40:01","RECEIPT_NO":"85046\/26335","METER_NO":"'07097971555","ACCT_NAME":"VALERIA BREL","ACCT_NO":"P06487400","VOUCHER_NO":"6797 5786 5234 5462 0826","TOTAL_KWH":"150.0","TOTAL_VALUE":"$39.60"},{"ISSUE_DATE":"Sep 8, 2023 16:40:12","RECEIPT_NO":"85046\/26336","METER_NO":"'07107717956","ACCT_NAME":"SARAH RUBARIO","ACCT_NO":"P06507900","VOUCHER_NO":"3756 7181 7173 3649 1735","TOTAL_KWH":"150.0","TOTAL_VALUE":"$39.60"},{"ISSUE_DATE":"Sep 8, 2023 16:40:23","RECEIPT_NO":"85046\/26337","METER_NO":"'07110219214","ACCT_NAME":"DESIREE MAD","ACCT_NO":"P06529900","VOUCHER_NO":"4405 9042 6695 0693 5555","TOTAL_KWH":"150.0","TOTAL_VALUE":"$39.60"},{"ISSUE_DATE":"Sep 8, 2023 16:40:35","RECEIPT_NO":"85046\/26338","METER_NO":"'07110214991","ACCT_NAME":"FREDRICK ANTHONIO","ACCT_NO":"P06532800","VOUCHER_NO":"4681 8919 0953 7248 5689","TOTAL_KWH":"114.6","TOTAL_VALUE":"$39.60"},{"ISSUE_DATE":"Sep 8, 2023 16:40:50","RECEIPT_NO":"85046\/26339","METER_NO":"'07147929066","ACCT_NAME":"REBECCA I. HASINTO","ACCT_NO":"P06697700","VOUCHER_NO":"0920 4207 0215 5160 1838","TOTAL_KWH":"114.6","TOTAL_VALUE":"$39.60"},{"ISSUE_DATE":"Sep 8, 2023 16:42:06","RECEIPT_NO":"85046\/26340","METER_NO":"'07147916410","ACCT_NAME":"NGIRATRANG KYOTA","ACCT_NO":"P06706300","VOUCHER_NO":"1572 3124 6344 6917 1617","TOTAL_KWH":"132.1","TOTAL_VALUE":"$39.60"},{"ISSUE_DATE":"Sep 8, 2023 16:42:19","RECEIPT_NO":"85046\/26341","METER_NO":"'07147945385","ACCT_NAME":"DILUBECH SAMIL","ACCT_NO":"P06652900","VOUCHER_NO":"2925 9861 5595 8621 0612","TOTAL_KWH":"135.4","TOTAL_VALUE":"$39.60"},{"ISSUE_DATE":"Sep 8, 2023 16:42:29","RECEIPT_NO":"85046\/26342","METER_NO":"'07057816394","ACCT_NAME":"REMASCH MADRACHELUIB","ACCT_NO":"P06568300","VOUCHER_NO":"6495 8575 0179 6188 4548","TOTAL_KWH":"150.0","TOTAL_VALUE":"$39.60"},{"ISSUE_DATE":"Sep 8, 2023 16:42:44","RECEIPT_NO":"85046\/26343","METER_NO":"'07053084658","ACCT_NAME":"GRANT NGOTEL UEHARA","ACCT_NO":"P06203900","VOUCHER_NO":"0733 3643 7521 8309 6171","TOTAL_KWH":"114.6","TOTAL_VALUE":"$39.60"},{"ISSUE_DATE":"Sep 8, 2023 16:43:05","RECEIPT_NO":"85046\/26344","METER_NO":"'07147927748","ACCT_NAME":"ERIK KLOULUBAK","ACCT_NO":"P06661800","VOUCHER_NO":"1923 2519 1000 4065 5162","TOTAL_KWH":"143.9","TOTAL_VALUE":"$37.99"},{"ISSUE_DATE":"Sep 8, 2023 16:43:18","RECEIPT_NO":"85046\/26345","METER_NO":"'07050106603","ACCT_NAME":"NARUO NGIRNGEMIUSECH","ACCT_NO":"P06354000","VOUCHER_NO":"0999 4322 4053 4017 7277","TOTAL_KWH":"114.6","TOTAL_VALUE":"$39.60"},{"ISSUE_DATE":"Sep 8, 2023 16:43:30","RECEIPT_NO":"85046\/26346","METER_NO":"'07110218786","ACCT_NAME":"CHERYLENE RENGULBAI","ACCT_NO":"P06537400","VOUCHER_NO":"0556 2272 0529 2874 9203","TOTAL_KWH":"118.9","TOTAL_VALUE":"$39.60"},{"ISSUE_DATE":"Sep 8, 2023 16:43:40","RECEIPT_NO":"85046\/26347","METER_NO":"'07057779352","ACCT_NAME":"VERNON MIKEL","ACCT_NO":"P06301400","VOUCHER_NO":"6957 1309 3707 7340 2778","TOTAL_KWH":"114.6","TOTAL_VALUE":"$39.60"},{"ISSUE_DATE":"Sep 8, 2023 16:43:51","RECEIPT_NO":"85046\/26348","METER_NO":"'07110214728","ACCT_NAME":"ANDRES THING","ACCT_NO":"P06238300","VOUCHER_NO":"3573 0512 2559 8523 9124","TOTAL_KWH":"114.6","TOTAL_VALUE":"$39.60"},{"ISSUE_DATE":"Sep 8, 2023 16:48:56","RECEIPT_NO":"85046\/26349","METER_NO":"'07097965250","ACCT_NAME":"JOHN MENGIDAB","ACCT_NO":"P06436100","VOUCHER_NO":"2607 8409 1039 6476 7425","TOTAL_KWH":"129.6","TOTAL_VALUE":"$39.60"},{"ISSUE_DATE":"Sep 8, 2023 16:49:16","RECEIPT_NO":"85046\/26350","METER_NO":"'07097963636","ACCT_NAME":"OPDULIA MALSOL","ACCT_NO":"P06422000","VOUCHER_NO":"4364 7947 6445 8508 7367","TOTAL_KWH":"150.0","TOTAL_VALUE":"$39.60"},{"ISSUE_DATE":"Sep 8, 2023 16:49:28","RECEIPT_NO":"85046\/26351","METER_NO":"'07147949916","ACCT_NAME":"HECTOR FRASER","ACCT_NO":"P06224500","VOUCHER_NO":"0700 7302 5081 8696 9330","TOTAL_KWH":"132.1","TOTAL_VALUE":"$39.60"},{"ISSUE_DATE":"Sep 8, 2023 16:50:07","RECEIPT_NO":"85046\/26352","METER_NO":"'07147910579","ACCT_NAME":"JERRY SINGEO RESIDENCE","ACCT_NO":"P06294300","VOUCHER_NO":"3855 2610 2315 7925 4126","TOTAL_KWH":"114.6","TOTAL_VALUE":"$39.60"},{"ISSUE_DATE":"Sep 8, 2023 16:50:19","RECEIPT_NO":"85046\/26353","METER_NO":"'07097963826","ACCT_NAME":"PATRICIA ANTONIO","ACCT_NO":"P06423900","VOUCHER_NO":"3996 1875 8897 3327 0828","TOTAL_KWH":"125.0","TOTAL_VALUE":"$39.60"},{"ISSUE_DATE":"Sep 8, 2023 16:50:36","RECEIPT_NO":"85046\/26354","METER_NO":"'07147943380","ACCT_NAME":"UCHARM MCARTHUR","ACCT_NO":"P06198400","VOUCHER_NO":"5675 5443 2731 6379 6116","TOTAL_KWH":"132.1","TOTAL_VALUE":"$39.60"},{"ISSUE_DATE":"Sep 8, 2023 16:51:43","RECEIPT_NO":"85046\/26355","METER_NO":"'07110218711","ACCT_NAME":"ELIZABETH CRUZ","ACCT_NO":"P06537300","VOUCHER_NO":"6820 9142 1410 2122 8073","TOTAL_KWH":"150.0","TOTAL_VALUE":"$39.60"},{"ISSUE_DATE":"Sep 8, 2023 16:51:59","RECEIPT_NO":"85046\/26356","METER_NO":"'07097971670","ACCT_NAME":"ALFONS NAGATA UPSTAIRS","ACCT_NO":"P06488100","VOUCHER_NO":"2855 6229 1824 5900 8845","TOTAL_KWH":"114.6","TOTAL_VALUE":"$39.60"},{"ISSUE_DATE":"Sep 8, 2023 16:52:16","RECEIPT_NO":"85046\/26357","METER_NO":"'07110216103","ACCT_NAME":"LUCIO ISAAC JR.","ACCT_NO":"P06264900","VOUCHER_NO":"1421 2590 3718 5531 7624","TOTAL_KWH":"114.6","TOTAL_VALUE":"$39.60"},{"ISSUE_DATE":"Sep 8, 2023 16:52:28","RECEIPT_NO":"85046\/26358","METER_NO":"'07147944628","ACCT_NAME":"LEONORE MAX","ACCT_NO":"P06702300","VOUCHER_NO":"5256 4348 8791 1990 9939","TOTAL_KWH":"130.4","TOTAL_VALUE":"$39.60"},{"ISSUE_DATE":"Sep 8, 2023 16:52:40","RECEIPT_NO":"85046\/26359","METER_NO":"'07144542946","ACCT_NAME":"DONALYNN D.U. BUKUROU","ACCT_NO":"P06423100","VOUCHER_NO":"3594 3534 2790 9003 4249","TOTAL_KWH":"114.6","TOTAL_VALUE":"$39.60"},{"ISSUE_DATE":"Sep 8, 2023 16:52:51","RECEIPT_NO":"85046\/26360","METER_NO":"'07137643974","ACCT_NAME":"ESTERLITA DEMEI #2","ACCT_NO":"P06557900","VOUCHER_NO":"6859 5925 5474 9805 3428","TOTAL_KWH":"150.0","TOTAL_VALUE":"$39.60"},{"ISSUE_DATE":"Sep 8, 2023 16:53:01","RECEIPT_NO":"85046\/26361","METER_NO":"'07107716339","ACCT_NAME":"KERKIRS MASAYOSHI","ACCT_NO":"P06499600","VOUCHER_NO":"6244 6076 4419 0868 2676","TOTAL_KWH":"130.4","TOTAL_VALUE":"$39.60"},{"ISSUE_DATE":"Sep 8, 2023 16:53:16","RECEIPT_NO":"85046\/26362","METER_NO":"'07082735338","ACCT_NAME":"HENARO POLLOI","ACCT_NO":"P06376300","VOUCHER_NO":"3796 6981 5033 6881 0597","TOTAL_KWH":"150.0","TOTAL_VALUE":"$39.60"},{"ISSUE_DATE":"Sep 8, 2023 16:53:28","RECEIPT_NO":"85046\/26363","METER_NO":"'07147898550","ACCT_NAME":"ISAAC THEODORE","ACCT_NO":"P06634700","VOUCHER_NO":"4744 7598 2516 4108 3173","TOTAL_KWH":"150.0","TOTAL_VALUE":"$39.60"},{"ISSUE_DATE":"Sep 8, 2023 16:53:41","RECEIPT_NO":"85046\/26364","METER_NO":"'37263736532","ACCT_NAME":"LILI ZEAN A. NGIRABLOSECH","ACCT_NO":"P06325000","VOUCHER_NO":"3896 5784 2080 7186 3129","TOTAL_KWH":"127.7","TOTAL_VALUE":"$39.60"},{"ISSUE_DATE":"Sep 8, 2023 16:54:04","RECEIPT_NO":"85046\/26365","METER_NO":"'07057814738","ACCT_NAME":"CALVIN MASAMI","ACCT_NO":"P06250700","VOUCHER_NO":"0667 7997 4114 7059 7181","TOTAL_KWH":"142.5","TOTAL_VALUE":"$37.62"},{"ISSUE_DATE":"Sep 8, 2023 16:54:23","RECEIPT_NO":"85046\/26366","METER_NO":"'07110879751","ACCT_NAME":"ANN LUND OR TRES ILILAU","ACCT_NO":"P06586100","VOUCHER_NO":"5627 8207 0634 7540 9061","TOTAL_KWH":"123.2","TOTAL_VALUE":"$39.60"},{"ISSUE_DATE":"Sep 8, 2023 16:54:34","RECEIPT_NO":"85046\/26367","METER_NO":"'07107716032","ACCT_NAME":"ELIA KUAL ","ACCT_NO":"P06497300","VOUCHER_NO":"0875 7798 5049 2959 5172","TOTAL_KWH":"132.1","TOTAL_VALUE":"$39.60"},{"ISSUE_DATE":"Sep 8, 2023 16:54:45","RECEIPT_NO":"85046\/26368","METER_NO":"'07107716776","ACCT_NAME":"LUCINDA OMISONG","ACCT_NO":"P06303300","VOUCHER_NO":"5061 7926 9738 8153 3142","TOTAL_KWH":"150.0","TOTAL_VALUE":"$39.60"},{"ISSUE_DATE":"Sep 8, 2023 16:54:57","RECEIPT_NO":"85046\/26369","METER_NO":"'07147948520","ACCT_NAME":"BARBINA OTIWII","ACCT_NO":"P06688200","VOUCHER_NO":"2263 7219 6865 5065 0398","TOTAL_KWH":"114.6","TOTAL_VALUE":"$39.60"},{"ISSUE_DATE":"Sep 8, 2023 16:55:08","RECEIPT_NO":"85046\/26370","METER_NO":"'07144537490","ACCT_NAME":"SINECIO AUGUSTINE","ACCT_NO":"P06598300","VOUCHER_NO":"2601 3356 0898 7361 0486","TOTAL_KWH":"114.6","TOTAL_VALUE":"$39.60"},{"ISSUE_DATE":"Sep 8, 2023 16:55:19","RECEIPT_NO":"85046\/26371","METER_NO":"'07147897487","ACCT_NAME":"TOSHIWO SECHARAIMUL","ACCT_NO":"P06284100","VOUCHER_NO":"5070 7604 2562 9375 8775","TOTAL_KWH":"150.0","TOTAL_VALUE":"$39.60"},{"ISSUE_DATE":"Sep 8, 2023 16:55:31","RECEIPT_NO":"85046\/26372","METER_NO":"'07057817319","ACCT_NAME":"PHILA MARUGG","ACCT_NO":"P06250300","VOUCHER_NO":"0453 9402 4061 4669 5975","TOTAL_KWH":"114.6","TOTAL_VALUE":"$39.60"},{"ISSUE_DATE":"Sep 8, 2023 16:55:45","RECEIPT_NO":"85046\/26373","METER_NO":"'07097965193","ACCT_NAME":"ELSA SUGAR","ACCT_NO":"P06477300","VOUCHER_NO":"0820 3736 3506 7428 8119","TOTAL_KWH":"127.7","TOTAL_VALUE":"$39.60"},{"ISSUE_DATE":"Sep 8, 2023 16:55:57","RECEIPT_NO":"85046\/26374","METER_NO":"'07077091853","ACCT_NAME":"ROCKY BAYAN","ACCT_NO":"P06336800","VOUCHER_NO":"1728 2864 8980 3244 5818","TOTAL_KWH":"132.1","TOTAL_VALUE":"$39.60"},{"ISSUE_DATE":"Sep 8, 2023 16:56:08","RECEIPT_NO":"85046\/26375","METER_NO":"'07137644766","ACCT_NAME":"RECHESENGEL IYECHAD","ACCT_NO":"P06563500","VOUCHER_NO":"4034 4714 0257 7314 6960","TOTAL_KWH":"132.1","TOTAL_VALUE":"$39.60"},{"ISSUE_DATE":"Sep 8, 2023 16:56:20","RECEIPT_NO":"85046\/26376","METER_NO":"'07147915974","ACCT_NAME":"SCARLET NAMBERT","ACCT_NO":"P06221900","VOUCHER_NO":"1639 1289 5141 7886 7323","TOTAL_KWH":"114.6","TOTAL_VALUE":"$39.60"},{"ISSUE_DATE":"Sep 8, 2023 16:58:54","RECEIPT_NO":"85046\/26377","METER_NO":"'37263743561","ACCT_NAME":"NOLAN REBLUUD","ACCT_NO":"P06628500","VOUCHER_NO":"7110 8811 7518 4995 8846","TOTAL_KWH":"150.0","TOTAL_VALUE":"$39.60"},{"ISSUE_DATE":"Sep 8, 2023 16:59:48","RECEIPT_NO":"85046\/26378","METER_NO":"'07097968270","ACCT_NAME":"PALAU HOUSING #10","ACCT_NO":"P06461700","VOUCHER_NO":"1329 0410 4757 8939 8560","TOTAL_KWH":"132.1","TOTAL_VALUE":"$39.60"},{"ISSUE_DATE":"Sep 8, 2023 17:00:01","RECEIPT_NO":"85046\/26379","METER_NO":"'07053084294","ACCT_NAME":"SADARIA LIROW-DOWNSTAIRS","ACCT_NO":"P06226700","VOUCHER_NO":"4034 4709 3077 3467 6974","TOTAL_KWH":"143.4","TOTAL_VALUE":"$39.60"},{"ISSUE_DATE":"Sep 8, 2023 17:00:13","RECEIPT_NO":"85046\/26380","METER_NO":"'07057819414","ACCT_NAME":"TORIBIONG TENGOLL C\/O FUANES NGIRCHOMLEI","ACCT_NO":"P06293300","VOUCHER_NO":"1114 3315 4434 1029 9371","TOTAL_KWH":"117.5","TOTAL_VALUE":"$39.60"},{"ISSUE_DATE":"Sep 8, 2023 17:00:24","RECEIPT_NO":"85046\/26381","METER_NO":"'07144545261","ACCT_NAME":"GINALYNE TOWAI","ACCT_NO":"P06603500","VOUCHER_NO":"3207 2226 6523 3993 6202","TOTAL_KWH":"138.6","TOTAL_VALUE":"$39.60"},{"ISSUE_DATE":"Sep 8, 2023 17:00:35","RECEIPT_NO":"85046\/26382","METER_NO":"'07144543159","ACCT_NAME":"VICKERY SNGEBARD","ACCT_NO":"P06622200","VOUCHER_NO":"5942 9870 8719 8765 7759","TOTAL_KWH":"150.0","TOTAL_VALUE":"$39.60"},{"ISSUE_DATE":"Sep 8, 2023 17:00:46","RECEIPT_NO":"85046\/26383","METER_NO":"'07077095508","ACCT_NAME":"VERONICA ARBEDUL","ACCT_NO":"P06227500","VOUCHER_NO":"1143 5557 5235 7882 9006","TOTAL_KWH":"132.1","TOTAL_VALUE":"$39.60"},{"ISSUE_DATE":"Sep 8, 2023 17:00:57","RECEIPT_NO":"85046\/26384","METER_NO":"'07144544702","ACCT_NAME":"MAX AND LEAH PETRUS HOME 2","ACCT_NO":"P06615700","VOUCHER_NO":"5035 1153 0850 5858 7076","TOTAL_KWH":"107.7","TOTAL_VALUE":"$39.60"},{"ISSUE_DATE":"Sep 8, 2023 17:01:09","RECEIPT_NO":"85046\/26385","METER_NO":"'07110878464","ACCT_NAME":"LYDIA REKLAI","ACCT_NO":"P06375400","VOUCHER_NO":"0099 0888 4190 7882 6599","TOTAL_KWH":"123.2","TOTAL_VALUE":"$39.60"},{"ISSUE_DATE":"Sep 8, 2023 17:01:18","RECEIPT_NO":"85046\/26386","METER_NO":"'07147943331","ACCT_NAME":"NADIA BENHART","ACCT_NO":"P06286000","VOUCHER_NO":"5735 6611 0583 0606 3708","TOTAL_KWH":"105.9","TOTAL_VALUE":"$39.60"},{"ISSUE_DATE":"Sep 8, 2023 17:01:29","RECEIPT_NO":"85046\/26387","METER_NO":"'07110897142","ACCT_NAME":"EMERITA KERRADEL","ACCT_NO":"P06543100","VOUCHER_NO":"4341 3444 0740 9634 8019","TOTAL_KWH":"114.6","TOTAL_VALUE":"$39.60"},{"ISSUE_DATE":"Sep 8, 2023 17:01:47","RECEIPT_NO":"85046\/26388","METER_NO":"'07097970367","ACCT_NAME":"HENIO KALUU","ACCT_NO":"P06475700","VOUCHER_NO":"3415 9325 7525 8963 2779","TOTAL_KWH":"150.0","TOTAL_VALUE":"$39.60"},{"ISSUE_DATE":"Sep 8, 2023 17:01:58","RECEIPT_NO":"85046\/26389","METER_NO":"'07147927763","ACCT_NAME":"MONALIZA RECHEUNGEL","ACCT_NO":"P06661400","VOUCHER_NO":"5639 5187 1195 5039 5498","TOTAL_KWH":"114.6","TOTAL_VALUE":"$39.60"},{"ISSUE_DATE":"Sep 8, 2023 17:02:08","RECEIPT_NO":"85046\/26390","METER_NO":"'07097966316","ACCT_NAME":"SANTOS THEODORE","ACCT_NO":"P06444700","VOUCHER_NO":"7325 6981 0811 8174 2777","TOTAL_KWH":"150.0","TOTAL_VALUE":"$39.60"},{"ISSUE_DATE":"Sep 8, 2023 17:02:18","RECEIPT_NO":"85046\/26391","METER_NO":"'07097970110","ACCT_NAME":"DORCAS NGIRUCHELBAD","ACCT_NO":"P06293800","VOUCHER_NO":"0822 4499 4245 8470 4993","TOTAL_KWH":"132.1","TOTAL_VALUE":"$39.60"},{"ISSUE_DATE":"Sep 8, 2023 17:02:31","RECEIPT_NO":"85046\/26392","METER_NO":"'07077095680","ACCT_NAME":"KUTERBIS KUTERMALEI","ACCT_NO":"P06365600","VOUCHER_NO":"0089 5999 1766 0294 8337","TOTAL_KWH":"114.6","TOTAL_VALUE":"$39.60"},{"ISSUE_DATE":"Sep 8, 2023 17:02:43","RECEIPT_NO":"85046\/26393","METER_NO":"'07097965052","ACCT_NAME":"RODNEY SUNGINO","ACCT_NO":"P06433300","VOUCHER_NO":"5700 5119 5860 3019 8099","TOTAL_KWH":"114.6","TOTAL_VALUE":"$39.60"},{"ISSUE_DATE":"Sep 8, 2023 17:02:52","RECEIPT_NO":"85046\/26394","METER_NO":"'07097964402","ACCT_NAME":"EDWINA NGIRAILILD","ACCT_NO":"P06428200","VOUCHER_NO":"7163 3467 4139 4534 9024","TOTAL_KWH":"114.6","TOTAL_VALUE":"$39.60"},{"ISSUE_DATE":"Sep 8, 2023 17:03:03","RECEIPT_NO":"85046\/26395","METER_NO":"'07147949049","ACCT_NAME":"ANANIAS BULTEDAOB 2","ACCT_NO":"P06689600","VOUCHER_NO":"1448 3672 5558 1590 5673","TOTAL_KWH":"135.4","TOTAL_VALUE":"$39.60"},{"ISSUE_DATE":"Sep 8, 2023 17:03:55","RECEIPT_NO":"85046\/26396","METER_NO":"'07050106637","ACCT_NAME":"CHERRY ETPISON","ACCT_NO":"P06353500","VOUCHER_NO":"6248 9793 9428 5494 7921","TOTAL_KWH":"114.6","TOTAL_VALUE":"$39.60"},{"ISSUE_DATE":"Sep 8, 2023 17:04:10","RECEIPT_NO":"85046\/26397","METER_NO":"'07110219586","ACCT_NAME":"CHERRIE SABURO","ACCT_NO":"P06528600","VOUCHER_NO":"0132 8484 0374 2084 8769","TOTAL_KWH":"128.7","TOTAL_VALUE":"$39.60"},{"ISSUE_DATE":"Sep 8, 2023 17:04:24","RECEIPT_NO":"85046\/26398","METER_NO":"'07055923481","ACCT_NAME":"MONICA EBAS RSEI","ACCT_NO":"P06568500","VOUCHER_NO":"0022 2647 6542 4219 9639","TOTAL_KWH":"132.1","TOTAL_VALUE":"$39.60"},{"ISSUE_DATE":"Sep 8, 2023 17:04:36","RECEIPT_NO":"85046\/26399","METER_NO":"'07147944578","ACCT_NAME":"ABEL KURTERBIS","ACCT_NO":"P06694500","VOUCHER_NO":"5224 2454 8493 8706 5671","TOTAL_KWH":"114.6","TOTAL_VALUE":"$39.60"},{"ISSUE_DATE":"Sep 8, 2023 17:04:53","RECEIPT_NO":"85046\/26400","METER_NO":"'07110879223","ACCT_NAME":"WESLEY M. LEWIS","ACCT_NO":"P06582400","VOUCHER_NO":"6443 6258 6350 7159 3407","TOTAL_KWH":"150.0","TOTAL_VALUE":"$39.60"},{"ISSUE_DATE":"Sep 8, 2023 17:05:05","RECEIPT_NO":"85046\/26401","METER_NO":"'07147944081","ACCT_NAME":"SHIRLEY TULOP","ACCT_NO":"P06322000","VOUCHER_NO":"4593 6135 3451 5326 3749","TOTAL_KWH":"113.2","TOTAL_VALUE":"$39.60"},{"ISSUE_DATE":"Sep 8, 2023 17:05:23","RECEIPT_NO":"85046\/26402","METER_NO":"'07097969088","ACCT_NAME":"MARGIE BLAILES","ACCT_NO":"P06218400","VOUCHER_NO":"4436 3095 6745 1720 1332","TOTAL_KWH":"114.6","TOTAL_VALUE":"$39.60"},{"ISSUE_DATE":"Sep 8, 2023 17:05:53","RECEIPT_NO":"85046\/26403","METER_NO":"'07144545873","ACCT_NAME":"OUALAI POLYCARP","ACCT_NO":"P06610100","VOUCHER_NO":"2002 3633 9377 8347 6102","TOTAL_KWH":"71.1","TOTAL_VALUE":"$18.78"},{"ISSUE_DATE":"Sep 8, 2023 17:06:10","RECEIPT_NO":"85046\/26404","METER_NO":"'37263736748","ACCT_NAME":"KYOKO SUMANG","ACCT_NO":"P06721900","VOUCHER_NO":"3171 7432 3732 5022 0351","TOTAL_KWH":"114.6","TOTAL_VALUE":"$39.60"},{"ISSUE_DATE":"Sep 8, 2023 17:06:21","RECEIPT_NO":"85046\/26405","METER_NO":"'07101015670","ACCT_NAME":"ROMAN REMOKET","ACCT_NO":"P06401400","VOUCHER_NO":"6710 1399 1230 0094 3536","TOTAL_KWH":"114.6","TOTAL_VALUE":"$39.60"},{"ISSUE_DATE":"Sep 8, 2023 17:06:33","RECEIPT_NO":"85046\/26406","METER_NO":"'07144543084","ACCT_NAME":"ANANIAS BULTEDAOB","ACCT_NO":"P06195900","VOUCHER_NO":"5821 4935 4657 3278 6019","TOTAL_KWH":"114.6","TOTAL_VALUE":"$39.60"},{"ISSUE_DATE":"Sep 8, 2023 17:06:46","RECEIPT_NO":"85046\/26407","METER_NO":"'07097964444","ACCT_NAME":"CHRISTINA PAULIS","ACCT_NO":"P06428800","VOUCHER_NO":"2388 8435 1748 2824 6459","TOTAL_KWH":"114.6","TOTAL_VALUE":"$39.60"},{"ISSUE_DATE":"Sep 8, 2023 17:06:57","RECEIPT_NO":"85046\/26408","METER_NO":"'07147910793","ACCT_NAME":"SHELLY IMETENGEL","ACCT_NO":"P06508500","VOUCHER_NO":"0659 7628 5671 5886 8636","TOTAL_KWH":"114.6","TOTAL_VALUE":"$39.60"},{"ISSUE_DATE":"Sep 8, 2023 17:07:10","RECEIPT_NO":"85046\/26409","METER_NO":"'07097963388","ACCT_NAME":"MELISSA K. MALSOL","ACCT_NO":"P06420400","VOUCHER_NO":"0098 8214 9940 3134 8642","TOTAL_KWH":"150.0","TOTAL_VALUE":"$39.60"},{"ISSUE_DATE":"Sep 8, 2023 17:07:21","RECEIPT_NO":"85046\/26410","METER_NO":"'07107716404","ACCT_NAME":"JENNIFER GERMANCE","ACCT_NO":"P06499800","VOUCHER_NO":"1997 4763 1858 8863 9242","TOTAL_KWH":"114.6","TOTAL_VALUE":"$39.60"},{"ISSUE_DATE":"Sep 8, 2023 17:07:36","RECEIPT_NO":"85046\/26411","METER_NO":"'07147910827","ACCT_NAME":"EUSEVIA EUNGEL","ACCT_NO":"P06198100","VOUCHER_NO":"6383 9117 4610 9640 9013","TOTAL_KWH":"114.6","TOTAL_VALUE":"$39.60"},{"ISSUE_DATE":"Sep 8, 2023 17:34:41","RECEIPT_NO":"85046\/26413","METER_NO":"'07110215196","ACCT_NAME":"PAULINE KUMAICHI","ACCT_NO":"P06523900","VOUCHER_NO":"0713 1389 9256 2472 5782","TOTAL_KWH":"150.0","TOTAL_VALUE":"$39.60"}]